[
  {
    "crush": "pc",
    "damage": "12 (12)",
    "gif": "",
    "id": "Jack-8-2+3",
    "image": "",
    "input": "2+3",
    "name": "Heat Burst",
    "notes": "Heat Burst\nPower crush",
    "on_block": "+1",
    "on_ch": "",
    "on_hit": "+2c",
    "recovery": "",
    "short_notes": "",
    "startup": "i16",
    "tags": "hb pc",
    "target": "m",
    "video": ""
  },
  {
    "crush": "pc",
    "damage": "50",
    "gif": "",
    "id": "Jack-8-H.2+3",
    "image": "",
    "input": "H.2+3",
    "name": "Meteor Raid",
    "notes": "* Heat Smash\n* Balcony Break\nPower crush",
    "on_block": "-9",
    "on_ch": "",
    "on_hit": "-2d (-12)",
    "recovery": "",
    "short_notes": "",
    "startup": "i10",
    "tags": "hs bbr pc",
    "target": "h,m,t",
    "video": ""
  },
  {
    "crush": "pc8~",
    "damage": "55+",
    "gif": "",
    "id": "Jack-8-R.df+1+2",
    "image": "",
    "input": "R.df+1+2",
    "name": "Terraforming Cannon",
    "notes": "* Rage Art\n* Damage increases with lower health\n* Erases opponent's recoverable health on hit\nPower crush 8~",
    "on_block": "-15",
    "on_ch": "",
    "on_hit": "+0d",
    "recovery": "",
    "short_notes": "* Rage Art\n* Damage increases with lower health\n* Erases opponent's recoverable health on hit",
    "startup": "i20",
    "tags": "pc8~",
    "target": "m,t",
    "video": ""
  },
  {
    "crush": "",
    "damage": "10",
    "gif": "",
    "id": "Jack-8-1",
    "image": "",
    "input": "1",
    "name": "Jab",
    "notes": "",
    "on_block": "-2",
    "on_ch": "+9",
    "on_hit": "+6",
    "recovery": "",
    "short_notes": "",
    "startup": "i12",
    "tags": "",
    "target": "h",
    "video": ""
  },
  {
    "crush": "",
    "damage": "10,22",
    "gif": "",
    "id": "Jack-8-1,1",
    "image": "",
    "input": "1,1",
    "name": "Jab &gt; Jackhammer",
    "notes": "* Elbow\n* Combos from 1st hit\n* Transition to GMH with D\n* (+4 oB, +8c oH, +16d)",
    "on_block": "-14c",
    "on_ch": "+12d",
    "on_hit": "+4c",
    "recovery": "",
    "short_notes": "* Combos from 1st hit\n* Transition to GMH with D\n* (+4 oB, +8c oH, +16d)",
    "startup": "i15",
    "tags": "elb",
    "target": "h,m",
    "video": ""
  },
  {
    "crush": "",
    "damage": "10,24",
    "gif": "",
    "id": "Jack-8-1,2",
    "image": "",
    "input": "1,2",
    "name": "Jab &gt; Stunning Hook",
    "notes": "Combos from 1st hit CH",
    "on_block": "-2",
    "on_ch": "",
    "on_hit": "+30a",
    "recovery": "",
    "short_notes": "Combos from 1st hit CH",
    "startup": "i19",
    "tags": "",
    "target": "h,h",
    "video": ""
  },
  {
    "crush": "",
    "damage": "10",
    "gif": "",
    "id": "Jack-8-2",
    "image": "",
    "input": "2",
    "name": "",
    "notes": "",
    "on_block": "+1",
    "on_ch": "",
    "on_hit": "+9",
    "recovery": "",
    "short_notes": "",
    "startup": "i11",
    "tags": "",
    "target": "h",
    "video": ""
  },
  {
    "crush": "",
    "damage": "10,12",
    "gif": "",
    "id": "Jack-8-2,1",
    "image": "",
    "input": "2,1",
    "name": "",
    "notes": "* Elbow\n* Combos from 1st hit",
    "on_block": "-3",
    "on_ch": "",
    "on_hit": "+2",
    "recovery": "",
    "short_notes": "* Combos from 1st hit",
    "startup": "i16",
    "tags": "elb",
    "target": "h,m",
    "video": ""
  },
  {
    "crush": "",
    "damage": "10,12,20",
    "gif": "",
    "id": "Jack-8-2,1,2",
    "image": "",
    "input": "2,1,2",
    "name": "Jab Elbow Smash",
    "notes": "",
    "on_block": "-12",
    "on_ch": "",
    "on_hit": "+29a (+19)",
    "recovery": "r FC",
    "short_notes": "",
    "startup": "i33",
    "tags": "",
    "target": "h,m,m",
    "video": ""
  },
  {
    "crush": "",
    "damage": "10,12,10,6,6,6,20",
    "gif": "",
    "id": "Jack-8-2,1,1+2",
    "image": "",
    "input": "2,1,1+2",
    "name": "Piston Gun Fusillade",
    "notes": "Jails",
    "on_block": "-4",
    "on_ch": "",
    "on_hit": "+13d",
    "recovery": "",
    "short_notes": "Jails",
    "startup": "i33",
    "tags": "",
    "target": "h,m,h,h,h,h,h",
    "video": ""
  },
  {
    "crush": "",
    "damage": "10,18",
    "gif": "",
    "id": "Jack-8-2,3",
    "image": "",
    "input": "2,3",
    "name": "Mimesis Savage Knee",
    "notes": "* Knee\n* 2nd hit Balcony Break on CH",
    "on_block": "-13",
    "on_ch": "+30d (+22)",
    "on_hit": "+5",
    "recovery": "",
    "short_notes": "* 2nd hit Balcony Break on CH",
    "startup": "i19",
    "tags": "kne",
    "target": "h,m",
    "video": ""
  },
  {
    "crush": "",
    "damage": "8,14",
    "gif": "",
    "id": "Jack-8-1+2",
    "image": "",
    "input": "1+2",
    "name": "Tornado Punch",
    "notes": "* Tornado\n* Instant Tornado\n* Homing",
    "on_block": "-13",
    "on_ch": "",
    "on_hit": "+67a (+51)",
    "recovery": "",
    "short_notes": "* Instant Tornado",
    "startup": "i15",
    "tags": "trn hom",
    "target": "m,m",
    "video": ""
  },
  {
    "crush": "",
    "damage": "",
    "gif": "",
    "id": "Jack-8-1+4",
    "image": "",
    "input": "1+4",
    "name": "",
    "notes": "* Alternate input hcf+1\n* 1+4 can be held for up to 5 spins (or multiple 360 motions)",
    "on_block": "",
    "on_ch": "",
    "on_hit": "",
    "recovery": "",
    "short_notes": "* Alternate input hcf+1\n* 1+4 can be held for up to 5 spins (or multiple 360 motions)",
    "startup": "i22~",
    "tags": "",
    "target": "",
    "video": ""
  },
  {
    "crush": "",
    "damage": "35/45/55/199",
    "gif": "",
    "id": "Jack-8-1+4*,1",
    "image": "",
    "input": "1+4*,1",
    "name": "Gigaton Punch (2/3/4/5 spins)",
    "notes": "* Balcony Break\n* Unblockable",
    "on_block": "!",
    "on_ch": "",
    "on_hit": "+70d",
    "recovery": "",
    "short_notes": "* Unblockable",
    "startup": "i17(68/93/118~)",
    "tags": "bbr",
    "target": "m",
    "video": ""
  },
  {
    "crush": "",
    "damage": "25 (30)",
    "gif": "",
    "id": "Jack-8-1+4,1",
    "image": "",
    "input": "1+4,1",
    "name": "Gigaton Punch",
    "notes": "* Balcony Break\n* Chip damage on block\n* Alternate input hcf+1 to do 5 more damage",
    "on_block": "+21g",
    "on_ch": "+39d (-8)",
    "on_hit": "+7a (-2)",
    "recovery": "",
    "short_notes": "* Alternate input hcf+1 to do 5 more damage",
    "startup": "i17(43~)",
    "tags": "bbr chp",
    "target": "m",
    "video": ""
  },
  {
    "crush": "",
    "damage": "21",
    "gif": "",
    "id": "Jack-8-1+4,df+1",
    "image": "",
    "input": "1+4,df+1",
    "name": "Windup Uppercut",
    "notes": "* Tornado\n* Alternate input hcf,df+1",
    "on_block": "-17",
    "on_ch": "",
    "on_hit": "+52a (+42)",
    "recovery": "",
    "short_notes": "* Alternate input hcf,df+1",
    "startup": "i21(41~)",
    "tags": "trn",
    "target": "m",
    "video": ""
  },
  {
    "crush": "",
    "damage": "36",
    "gif": "",
    "id": "Jack-8-1+4:df+1",
    "image": "",
    "input": "1+4:df+1",
    "name": "Prime Windup Uppercut",
    "notes": "* Just Frame version of 1+4,df+1 (hcf,df+1)\n* Tornado\n* Instant Tornado\n* Alternate input hcf:df+1",
    "on_block": "-17",
    "on_ch": "",
    "on_hit": "+66a (+50)",
    "recovery": "",
    "short_notes": "* Just Frame version of 1+4,df+1 (hcf,df+1)\n* Instant Tornado\n* Alternate input hcf:df+1",
    "startup": "i21(41~)",
    "tags": "trn",
    "target": "m",
    "video": ""
  },
  {
    "crush": "pc",
    "damage": "",
    "gif": "",
    "id": "Jack-8-3+4",
    "image": "",
    "input": "3+4",
    "name": "Gamma Howl (Gamma Charge)",
    "notes": "* When timed with opponent attack, or absorbing an attack, shift to Gamma Charge\n* Recover Heat and recoverable health when absorbing an attack\n* Gamma Charge is always\nin effect during Heat\n* Alternate input: ws3+4\nPower crush",
    "on_block": "",
    "on_ch": "",
    "on_hit": "",
    "recovery": "",
    "short_notes": "* When timed with opponent attack, or absorbing an attack, shift to Gamma Charge\n* Recover Heat and recoverable health when absorbing an attack\n* Gamma Charge is always\nin effect during Heat\n* Alternate input: ws3+4",
    "startup": "",
    "tags": "pc",
    "target": "",
    "video": ""
  },
  {
    "crush": "",
    "damage": "13",
    "gif": "",
    "id": "Jack-8-f+1",
    "image": "",
    "input": "f+1",
    "name": "",
    "notes": "",
    "on_block": "-6",
    "on_ch": "",
    "on_hit": "+5",
    "recovery": "",
    "short_notes": "",
    "startup": "i14",
    "tags": "",
    "target": "m",
    "video": ""
  },
  {
    "crush": "",
    "damage": "13,25",
    "gif": "",
    "id": "Jack-8-f+1,1",
    "image": "",
    "input": "f+1,1",
    "name": "Impact Driver",
    "notes": "Combos from 1st hit",
    "on_block": "-7",
    "on_ch": "+40d (-7)",
    "on_hit": "+8d (-1)",
    "recovery": "",
    "short_notes": "Combos from 1st hit",
    "startup": "i25",
    "tags": "",
    "target": "m,h",
    "video": ""
  },
  {
    "crush": "",
    "damage": "13,12",
    "gif": "",
    "id": "Jack-8-f+1,2",
    "image": "",
    "input": "f+1,2",
    "name": "",
    "notes": "Combos from 1st hit",
    "on_block": "-6",
    "on_ch": "",
    "on_hit": "+5",
    "recovery": "",
    "short_notes": "Combos from 1st hit",
    "startup": "i22",
    "tags": "",
    "target": "m,h",
    "video": ""
  },
  {
    "crush": "",
    "damage": "13,12,12",
    "gif": "",
    "id": "Jack-8-f+1,2,1",
    "image": "",
    "input": "f+1,2,1",
    "name": "Drilling Engine",
    "notes": "* Tornado\n* Instant Tornado",
    "on_block": "-12",
    "on_ch": "",
    "on_hit": "+65a (+49)",
    "recovery": "",
    "short_notes": "* Instant Tornado",
    "startup": "i26",
    "tags": "trn",
    "target": "m,h,m",
    "video": ""
  },
  {
    "crush": "",
    "damage": "13,12,12",
    "gif": "",
    "id": "Jack-8-f+1,2,2",
    "image": "",
    "input": "f+1,2,2",
    "name": "Piston Gun Blaster",
    "notes": "* Can be charged to power up\n* Chip damage on block",
    "on_block": "+6",
    "on_ch": "",
    "on_hit": "+3d",
    "recovery": "",
    "short_notes": "* Can be charged to power up",
    "startup": "i33",
    "tags": "chp",
    "target": "m,h,m",
    "video": ""
  },
  {
    "crush": "",
    "damage": "13,12,12",
    "gif": "",
    "id": "Jack-8-f+1,2,2*",
    "image": "",
    "input": "f+1,2,2*",
    "name": "Piston Gun Blaster (charged)",
    "notes": "* Balcony Break\n* Wall crush\n* Chip damage on block",
    "on_block": "-12 (0 wall crush)",
    "on_ch": "",
    "on_hit": "+11d (-15)",
    "recovery": "",
    "short_notes": "",
    "startup": "i61",
    "tags": "bbr wc chp",
    "target": "m,h,m",
    "video": ""
  },
  {
    "crush": "",
    "damage": "22",
    "gif": "",
    "id": "Jack-8-f+2",
    "image": "",
    "input": "f+2",
    "name": "Pinpoint Assault",
    "notes": "",
    "on_block": "-12",
    "on_ch": "+32a (+24)",
    "on_hit": "+5",
    "recovery": "",
    "short_notes": "",
    "startup": "i10",
    "tags": "",
    "target": "h",
    "video": ""
  },
  {
    "crush": "",
    "damage": "18",
    "gif": "",
    "id": "Jack-8-f+3",
    "image": "",
    "input": "f+3",
    "name": "",
    "notes": "* Knee\n* Transition to GMH with D\n** (+2 oB, +16g oH)\n* Alternate input ws3",
    "on_block": "-9",
    "on_ch": "",
    "on_hit": "+5",
    "recovery": "",
    "short_notes": "* Transition to GMH with D\n** (+2 oB, +16g oH)\n* Alternate input ws3",
    "startup": "i15",
    "tags": "kne",
    "target": "m",
    "video": ""
  },
  {
    "crush": "",
    "damage": "18,20",
    "gif": "",
    "id": "Jack-8-f+3,2",
    "image": "",
    "input": "f+3,2",
    "name": "Two-Step Die",
    "notes": "* Balcony Break\n* Combos from 1st hit\n* Alternate input ws3,2",
    "on_block": "-9",
    "on_ch": "",
    "on_hit": "+44d (-14)",
    "recovery": "",
    "short_notes": "* Combos from 1st hit\n* Alternate input ws3,2",
    "startup": "i23",
    "tags": "bbr",
    "target": "m,h",
    "video": ""
  },
  {
    "crush": "",
    "damage": "18,20",
    "gif": "",
    "id": "Jack-8-f+3,1+2",
    "image": "",
    "input": "f+3,1+2",
    "name": "Machine Press",
    "notes": "* Combos from 1st hit CH\n* Alternate input ws3,1+2",
    "on_block": "-11c",
    "on_ch": "+48a",
    "on_hit": "+2d",
    "recovery": "",
    "short_notes": "* Combos from 1st hit CH\n* Alternate input ws3,1+2",
    "startup": "i25",
    "tags": "",
    "target": "m,m",
    "video": ""
  },
  {
    "crush": "",
    "damage": "80",
    "gif": "",
    "id": "Jack-8-f+4~1",
    "image": "",
    "input": "f+4~1",
    "name": "Dark Greeting",
    "notes": "Unblockable",
    "on_block": "!",
    "on_ch": "",
    "on_hit": "+5",
    "recovery": "",
    "short_notes": "Unblockable",
    "startup": "i65",
    "tags": "",
    "target": "h",
    "video": ""
  },
  {
    "crush": "",
    "damage": "30",
    "gif": "",
    "id": "Jack-8-f+4~1,2",
    "image": "",
    "input": "f+4~1,2",
    "name": "Sudden Elbow",
    "notes": "Elbow",
    "on_block": "+8",
    "on_ch": "",
    "on_hit": "+0d",
    "recovery": "",
    "short_notes": "",
    "startup": "i15 (66~)",
    "tags": "elb",
    "target": "m",
    "video": ""
  },
  {
    "crush": "pc",
    "damage": "12,20",
    "gif": "",
    "id": "Jack-8-f+1+2",
    "image": "",
    "input": "f+1+2",
    "name": "Rolling Death Crusher",
    "notes": "* Balcony Break\n* Chip damage on block\nPower crush",
    "on_block": "-12",
    "on_ch": "",
    "on_hit": "+32d (+6)",
    "recovery": "",
    "short_notes": "",
    "startup": "i27",
    "tags": "bbr chp pc",
    "target": "m,m",
    "video": ""
  },
  {
    "crush": "",
    "damage": "24",
    "gif": "",
    "id": "Jack-8-f+3+4",
    "image": "",
    "input": "f+3+4",
    "name": "Merkabah Headbutt",
    "notes": "* Headbutt\n* Transition to GMH with D\n** (-3 oB, +15g oH)",
    "on_block": "-11",
    "on_ch": "",
    "on_hit": "+9c",
    "recovery": "",
    "short_notes": "* Headbutt\n* Transition to GMH with D\n** (-3 oB, +15g oH)",
    "startup": "i22",
    "tags": "",
    "target": "m",
    "video": ""
  },
  {
    "crush": "",
    "damage": "12",
    "gif": "",
    "id": "Jack-8-df+1",
    "image": "",
    "input": "df+1",
    "name": "",
    "notes": "",
    "on_block": "-4",
    "on_ch": "+5",
    "on_hit": "+3",
    "recovery": "",
    "short_notes": "",
    "startup": "i14",
    "tags": "",
    "target": "m",
    "video": ""
  },
  {
    "crush": "",
    "damage": "12",
    "gif": "",
    "id": "Jack-8-df+1,1",
    "image": "",
    "input": "df+1,1",
    "name": "Overheat",
    "notes": "* Tornado\n* Balcony Break\n* Combos from 1st hit CH\n* Delayable",
    "on_block": "-11",
    "on_ch": "+72a (+56)",
    "on_hit": "+21cg",
    "recovery": "",
    "short_notes": "* Combos from 1st hit CH\n* Delayable",
    "startup": "i29",
    "tags": "trn bbr",
    "target": "m,m",
    "video": ""
  },
  {
    "crush": "",
    "damage": "1210",
    "gif": "",
    "id": "Jack-8-df+1,2",
    "image": "",
    "input": "df+1,2",
    "name": "",
    "notes": "*Jails\n* Combos from 1st hit CH\n* Delayable",
    "on_block": "-12",
    "on_ch": "",
    "on_hit": "-1",
    "recovery": "",
    "short_notes": "*Jails\n* Combos from 1st hit CH\n* Delayable",
    "startup": "i29",
    "tags": "",
    "target": "m,h",
    "video": ""
  },
  {
    "crush": "",
    "damage": "1210,2",
    "gif": "",
    "id": "Jack-8-df+1,2,1",
    "image": "",
    "input": "df+1,2,1",
    "name": "",
    "notes": "* Jails\n* On air hit +22a (+15)\n* Combos from 2nd hit\n* Combos from 1st hit CH",
    "on_block": "-10",
    "on_ch": "",
    "on_hit": "-2",
    "recovery": "",
    "short_notes": "* Jails\n* On air hit +22a (+15)\n* Combos from 2nd hit\n* Combos from 1st hit CH",
    "startup": "i15",
    "tags": "",
    "target": "m,h,h",
    "video": ""
  },
  {
    "crush": "",
    "damage": "1210,2,20",
    "gif": "",
    "id": "Jack-8-df+1,2,1,2",
    "image": "",
    "input": "df+1,2,1,2",
    "name": "Overdrive",
    "notes": "* Balcony Break\n* On air hit +12 (+5) \n* Combos from 2nd hit\n* Combos from 1st hit CH",
    "on_block": "-18",
    "on_ch": "",
    "on_hit": "+35d (-23)",
    "recovery": "",
    "short_notes": "* On air hit +12 (+5) \n* Combos from 2nd hit\n* Combos from 1st hit CH",
    "startup": "i9",
    "tags": "bbr",
    "target": "m,h,h,h",
    "video": ""
  },
  {
    "crush": "",
    "damage": "20",
    "gif": "",
    "id": "Jack-8-df+1+3",
    "image": "",
    "input": "df+1+3",
    "name": "Body Press",
    "notes": "{{}}",
    "on_block": "-11",
    "on_ch": "",
    "on_hit": "+0d~+19d",
    "recovery": "",
    "short_notes": "{{}}",
    "startup": "i30~49",
    "tags": "",
    "target": "sm",
    "video": ""
  },
  {
    "crush": "",
    "damage": "13",
    "gif": "",
    "id": "Jack-8-df+2",
    "image": "",
    "input": "df+2",
    "name": "Programmed Uppercut",
    "notes": "",
    "on_block": "-14",
    "on_ch": "",
    "on_hit": "+31a (+21)",
    "recovery": "",
    "short_notes": "",
    "startup": "i15",
    "tags": "",
    "target": "m",
    "video": ""
  },
  {
    "crush": "",
    "damage": "13,16",
    "gif": "",
    "id": "Jack-8-df+2,1",
    "image": "",
    "input": "df+2,1",
    "name": "Cosmic Sweeper",
    "notes": "* Transition to GMH with D\n** (+45a (+27) oH)\n* Can be charged to power up",
    "on_block": "-32",
    "on_ch": "",
    "on_hit": "+40a (+22)",
    "recovery": "",
    "short_notes": "* Transition to GMH with D\n** (+45a (+27) oH)\n* Can be charged to power up",
    "startup": "i21",
    "tags": "",
    "target": "m,h",
    "video": ""
  },
  {
    "crush": "",
    "damage": "13,16",
    "gif": "",
    "id": "Jack-8-df+2,1*",
    "image": "",
    "input": "df+2,1*",
    "name": "Cosmic Sweeper (charged)",
    "notes": "* Tornado\n* Transition to GMH with D\n** (+70a (+54) oH))",
    "on_block": "-46",
    "on_ch": "",
    "on_hit": "+69a (+53)",
    "recovery": "",
    "short_notes": "* Transition to GMH with D\n** (+70a (+54) oH))",
    "startup": "i35",
    "tags": "trn",
    "target": "m,h",
    "video": ""
  },
  {
    "crush": "",
    "damage": "16",
    "gif": "",
    "id": "Jack-8-df+3",
    "image": "",
    "input": "df+3",
    "name": "",
    "notes": "",
    "on_block": "-9",
    "on_ch": "",
    "on_hit": "+2",
    "recovery": "",
    "short_notes": "",
    "startup": "i16",
    "tags": "",
    "target": "m",
    "video": ""
  },
  {
    "crush": "",
    "damage": "1620",
    "gif": "",
    "id": "Jack-8-df+3,2",
    "image": "",
    "input": "df+3,2",
    "name": "Combine Harvester",
    "notes": "Balcony Break",
    "on_block": "-9",
    "on_ch": "",
    "on_hit": "+25d",
    "recovery": "",
    "short_notes": "",
    "startup": "i20",
    "tags": "bbr",
    "target": "m,h",
    "video": ""
  },
  {
    "crush": "",
    "damage": "17",
    "gif": "",
    "id": "Jack-8-df+4",
    "image": "",
    "input": "df+4",
    "name": "Mimesis Wrench Kick",
    "notes": "",
    "on_block": "-9",
    "on_ch": "+14c",
    "on_hit": "+5",
    "recovery": "",
    "short_notes": "",
    "startup": "i15",
    "tags": "",
    "target": "m",
    "video": ""
  },
  {
    "crush": "",
    "damage": "23",
    "gif": "",
    "id": "Jack-8-df+1+4",
    "image": "",
    "input": "df+1+4",
    "name": "Debugger",
    "notes": "* Homing\n* Alternate input b,db,d,df+1 to power up\n** (28 damage, i29)",
    "on_block": "-37",
    "on_ch": "",
    "on_hit": "+18d",
    "recovery": "",
    "short_notes": "* Alternate input b,db,d,df+1 to power up\n** (28 damage, i29)",
    "startup": "i34",
    "tags": "hom",
    "target": "l",
    "video": ""
  },
  {
    "crush": "",
    "damage": "26",
    "gif": "",
    "id": "Jack-8-df+2+3",
    "image": "",
    "input": "df+2+3",
    "name": "Megaton Blast",
    "notes": "* Balcony Break\n* Alternate input b,db,d,df+2 to power up\n** (31 damage, i22)",
    "on_block": "-9",
    "on_ch": "",
    "on_hit": "+31d (-5)",
    "recovery": "",
    "short_notes": "* Alternate input b,db,d,df+2 to power up\n** (31 damage, i22)",
    "startup": "i22",
    "tags": "bbr",
    "target": "m",
    "video": ""
  },
  {
    "crush": "",
    "damage": "28",
    "gif": "",
    "id": "Jack-8-df+3+4",
    "image": "",
    "input": "df+3+4",
    "name": "Dump Truck",
    "notes": "Balcony Break",
    "on_block": "-23",
    "on_ch": "",
    "on_hit": "+10a (+1)",
    "recovery": "",
    "short_notes": "",
    "startup": "i13",
    "tags": "bbr",
    "target": "m",
    "video": ""
  },
  {
    "crush": "",
    "damage": "5",
    "gif": "",
    "id": "Jack-8-d+1",
    "image": "",
    "input": "d+1",
    "name": "",
    "notes": "*",
    "on_block": "-5",
    "on_ch": "",
    "on_hit": "+6",
    "recovery": "rFC",
    "short_notes": "*",
    "startup": "i10",
    "tags": "",
    "target": "s",
    "video": ""
  },
  {
    "crush": "",
    "damage": "8",
    "gif": "",
    "id": "Jack-8-d+2",
    "image": "",
    "input": "d+2",
    "name": "",
    "notes": "* Alternate input FC.d+2",
    "on_block": "-4",
    "on_ch": "",
    "on_hit": "+7",
    "recovery": "rFC",
    "short_notes": "* Alternate input FC.d+2",
    "startup": "i11",
    "tags": "",
    "target": "s",
    "video": ""
  },
  {
    "crush": "",
    "damage": "12",
    "gif": "",
    "id": "Jack-8-d+3",
    "image": "",
    "input": "d+3",
    "name": "",
    "notes": "* Alternate input FC.d+3",
    "on_block": "-17",
    "on_ch": "",
    "on_hit": "-6",
    "recovery": "rFC",
    "short_notes": "* Alternate input FC.d+3",
    "startup": "i20",
    "tags": "",
    "target": "l",
    "video": ""
  },
  {
    "crush": "",
    "damage": "10",
    "gif": "",
    "id": "Jack-8-d+4",
    "image": "",
    "input": "d+4",
    "name": "",
    "notes": "* Alternate input FC.d+4",
    "on_block": "-15",
    "on_ch": "",
    "on_hit": "-4",
    "recovery": "rFC",
    "short_notes": "* Alternate input FC.d+4",
    "startup": "i16",
    "tags": "",
    "target": "l",
    "video": ""
  },
  {
    "crush": "",
    "damage": "28",
    "gif": "",
    "id": "Jack-8-d+1+2",
    "image": "",
    "input": "d+1+2",
    "name": "Double Axe",
    "notes": "*",
    "on_block": "-18",
    "on_ch": "",
    "on_hit": "+42a (+32)",
    "recovery": "",
    "short_notes": "*",
    "startup": "i27",
    "tags": "",
    "target": "m",
    "video": ""
  },
  {
    "crush": "",
    "damage": "18",
    "gif": "",
    "id": "Jack-8-Grounded face up d+1+2",
    "image": "",
    "input": "d+1+2",
    "name": "Get Up Punch",
    "notes": "* Recovers in SIT, then stands up",
    "on_block": "+18g",
    "on_ch": "",
    "on_hit": "+39d",
    "recovery": "SIT",
    "short_notes": "* Recovers in SIT, then stands up",
    "startup": "i28",
    "tags": "",
    "target": "m",
    "video": ""
  },
  {
    "crush": "",
    "damage": "",
    "gif": "",
    "id": "Jack-8-d+3+4",
    "image": "",
    "input": "d+3+4",
    "name": "Sit Down",
    "notes": "* Transitions to SIT (Sit Down)",
    "on_block": "",
    "on_ch": "",
    "on_hit": "",
    "recovery": "SIT",
    "short_notes": "* Transitions to SIT (Sit Down)",
    "startup": "",
    "tags": "",
    "target": "",
    "video": ""
  },
  {
    "crush": "cs",
    "damage": "5",
    "gif": "",
    "id": "Jack-8-db+1",
    "image": "",
    "input": "db+1",
    "name": "",
    "notes": "*\nHigh crush",
    "on_block": "-12",
    "on_ch": "",
    "on_hit": "+1",
    "recovery": "rFC",
    "short_notes": "*",
    "startup": "i13",
    "tags": "cs",
    "target": "l",
    "video": ""
  },
  {
    "crush": "cs",
    "damage": "5,5",
    "gif": "",
    "id": "Jack-8-db+1,1",
    "image": "",
    "input": "db+1,1",
    "name": "",
    "notes": "* Combos from 1st hit\nHigh crush",
    "on_block": "-12",
    "on_ch": "",
    "on_hit": "-1",
    "recovery": "rFC",
    "short_notes": "* Combos from 1st hit",
    "startup": "i16",
    "tags": "cs",
    "target": "l,l",
    "video": ""
  },
  {
    "crush": "cs",
    "damage": "5,5,5",
    "gif": "",
    "id": "Jack-8-db+1,1,1",
    "image": "",
    "input": "db+1,1,1",
    "name": "",
    "notes": "*\nHigh crush",
    "on_block": "-12",
    "on_ch": "",
    "on_hit": "-1",
    "recovery": "rFC",
    "short_notes": "*",
    "startup": "i16",
    "tags": "cs",
    "target": "l,l,l",
    "video": ""
  },
  {
    "crush": "",
    "damage": "5,5,5,21",
    "gif": "",
    "id": "Jack-8-db+1,1,1,2",
    "image": "",
    "input": "db+1,1,1,2",
    "name": "Machinegun Blast",
    "notes": "* Balcony Break",
    "on_block": "-11",
    "on_ch": "",
    "on_hit": "+43a (-4)",
    "recovery": "",
    "short_notes": "",
    "startup": "i19",
    "tags": "bbr",
    "target": "l,l,l,m",
    "video": ""
  },
  {
    "crush": "",
    "damage": "24",
    "gif": "",
    "id": "Jack-8-db+2",
    "image": "",
    "input": "db+2",
    "name": "Power Shovel",
    "notes": "* Can be charged to power up",
    "on_block": "-18",
    "on_ch": "+33d",
    "on_hit": "+3",
    "recovery": "",
    "short_notes": "* Can be charged to power up",
    "startup": "i22",
    "tags": "",
    "target": "l",
    "video": ""
  },
  {
    "crush": "",
    "damage": "30",
    "gif": "",
    "id": "Jack-8-db+2*",
    "image": "",
    "input": "db+2*",
    "name": "Power Shovel (charged)",
    "notes": "* Chip damage on block",
    "on_block": "-33",
    "on_ch": "",
    "on_hit": "+17d",
    "recovery": "",
    "short_notes": "",
    "startup": "i36",
    "tags": "chp",
    "target": "l",
    "video": ""
  },
  {
    "crush": "",
    "damage": "15",
    "gif": "",
    "id": "Jack-8-db+3",
    "image": "",
    "input": "db+3",
    "name": "Cossack Kick",
    "notes": "*",
    "on_block": "-20",
    "on_ch": "",
    "on_hit": "-9",
    "recovery": "",
    "short_notes": "*",
    "startup": "i21",
    "tags": "",
    "target": "l",
    "video": ""
  },
  {
    "crush": "",
    "damage": "15,21",
    "gif": "",
    "id": "Jack-8-db+3,1+2",
    "image": "",
    "input": "db+3, ... 1+2",
    "name": "Cossack Smash",
    "notes": "* Balcony Break",
    "on_block": "+14g",
    "on_ch": "",
    "on_hit": "+43a (-15)",
    "recovery": "",
    "short_notes": "",
    "startup": "i34",
    "tags": "bbr",
    "target": "l,h",
    "video": ""
  },
  {
    "crush": "",
    "damage": "15,4,5,5,5,5,21",
    "gif": "",
    "id": "Jack-8-db+3,d+1+2",
    "image": "",
    "input": "db+3, ... d+1+2",
    "name": "Cossack Compactor",
    "notes": "* Crouch throw (Unbreakable)\n* Can be executed after any hit of Cossack Kicks (DB+3,4,3...)",
    "on_block": "",
    "on_ch": "",
    "on_hit": "0",
    "recovery": "",
    "short_notes": "* Crouch throw (Unbreakable)\n* Can be executed after any hit of Cossack Kicks (DB+3,4,3...)",
    "startup": "i34",
    "tags": "",
    "target": "l,m (th)",
    "video": ""
  },
  {
    "crush": "",
    "damage": "15,12",
    "gif": "",
    "id": "Jack-8-db+3,4",
    "image": "",
    "input": "db+3,4",
    "name": "",
    "notes": "*",
    "on_block": "-16",
    "on_ch": "",
    "on_hit": "-9",
    "recovery": "",
    "short_notes": "*",
    "startup": "i27",
    "tags": "",
    "target": "l,l",
    "video": ""
  },
  {
    "crush": "",
    "damage": "15,12,12",
    "gif": "",
    "id": "Jack-8-db+3,4,3",
    "image": "",
    "input": "db+3,4,3",
    "name": "",
    "notes": "*",
    "on_block": "-19",
    "on_ch": "",
    "on_hit": "-8",
    "recovery": "",
    "short_notes": "*",
    "startup": "i27",
    "tags": "",
    "target": "l,l,l",
    "video": ""
  },
  {
    "crush": "",
    "damage": "15,12,12,12",
    "gif": "",
    "id": "Jack-8-db+3,4,3,4",
    "image": "",
    "input": "db+3,4,3,4",
    "name": "",
    "notes": "*",
    "on_block": "-16",
    "on_ch": "",
    "on_hit": "-5",
    "recovery": "",
    "short_notes": "*",
    "startup": "i27",
    "tags": "",
    "target": "l,l,l,l",
    "video": ""
  },
  {
    "crush": "",
    "damage": "15,12,12,12,12",
    "gif": "",
    "id": "Jack-8-db+3,4,3,4,3",
    "image": "",
    "input": "db+3,4,3,4,3",
    "name": "",
    "notes": "*",
    "on_block": "-19",
    "on_ch": "",
    "on_hit": "-8",
    "recovery": "",
    "short_notes": "*",
    "startup": "i27",
    "tags": "",
    "target": "l,l,l,l,l",
    "video": ""
  },
  {
    "crush": "",
    "damage": "15,12,12,12,12,12",
    "gif": "",
    "id": "Jack-8-db+3,4,3,4,3,4",
    "image": "",
    "input": "db+3,4,3,4,3,4",
    "name": "Cossack Kicks",
    "notes": "*",
    "on_block": "-16",
    "on_ch": "",
    "on_hit": "-5",
    "recovery": "",
    "short_notes": "*",
    "startup": "i27",
    "tags": "",
    "target": "l,l,l,l,l,l",
    "video": ""
  },
  {
    "crush": "cs",
    "damage": "14",
    "gif": "",
    "id": "Jack-8-db+4",
    "image": "",
    "input": "db+4",
    "name": "Big Boot",
    "notes": "*\nHigh crush",
    "on_block": "-13",
    "on_ch": "",
    "on_hit": "-2",
    "recovery": "rFC",
    "short_notes": "*",
    "startup": "i16",
    "tags": "cs",
    "target": "l",
    "video": ""
  },
  {
    "crush": "",
    "damage": "8,21",
    "gif": "",
    "id": "Jack-8-db1+2",
    "image": "",
    "input": "db+1+2",
    "name": "Megaton Earthquake",
    "notes": "*",
    "on_block": "-70",
    "on_ch": "",
    "on_hit": "-5d",
    "recovery": "",
    "short_notes": "*",
    "startup": "i18",
    "tags": "",
    "target": "l,l",
    "video": ""
  },
  {
    "crush": "",
    "damage": "17",
    "gif": "",
    "id": "Jack-8-b+1",
    "image": "",
    "input": "b+1",
    "name": "",
    "notes": "*",
    "on_block": "-11",
    "on_ch": "",
    "on_hit": "+8",
    "recovery": "",
    "short_notes": "*",
    "startup": "i20",
    "tags": "",
    "target": "m",
    "video": ""
  },
  {
    "crush": "",
    "damage": "17,17",
    "gif": "",
    "id": "Jack-8-b+1,2",
    "image": "",
    "input": "b+1,2",
    "name": "Double Biceps",
    "notes": "* Spike\n* Combos from 1st hit",
    "on_block": "-14",
    "on_ch": "+47a",
    "on_hit": "+15d",
    "recovery": "",
    "short_notes": "* Combos from 1st hit",
    "startup": "i26",
    "tags": "spk",
    "target": "m,m",
    "video": ""
  },
  {
    "crush": "",
    "damage": "27",
    "gif": "",
    "id": "Jack-8-b+2",
    "image": "",
    "input": "b+2",
    "name": "Piston Gun Assault",
    "notes": "* Heat Engager\n\n* Heat Dash +5, +36a(+26)\n\n* Balcony Break",
    "on_block": "+5",
    "on_ch": "",
    "on_hit": "+2d",
    "recovery": "",
    "short_notes": "\n* Heat Dash +5, +36a(+26)\n",
    "startup": "i19",
    "tags": "he bbr",
    "target": "m",
    "video": ""
  },
  {
    "crush": "",
    "damage": "40",
    "gif": "",
    "id": "Jack-8-b+2*",
    "image": "",
    "input": "b+2*",
    "name": "Piston Gun Assault (charged)",
    "notes": "* Heat Engager\n\n* Heat Dash +5, +36a(+26)\n\n* Balcony Break\n* Wall crush\n* Chip damage on block",
    "on_block": "-2 (+5 WC)",
    "on_ch": "",
    "on_hit": "+17a (+9)",
    "recovery": "",
    "short_notes": "\n* Heat Dash +5, +36a(+26)\n",
    "startup": "i35",
    "tags": "he bbr wc chp",
    "target": "m",
    "video": ""
  },
  {
    "crush": "",
    "damage": "14",
    "gif": "",
    "id": "Jack-8-b+3",
    "image": "",
    "input": "b+3",
    "name": "",
    "notes": "*",
    "on_block": "-9",
    "on_ch": "",
    "on_hit": "+2",
    "recovery": "",
    "short_notes": "*",
    "startup": "i16",
    "tags": "",
    "target": "m",
    "video": ""
  },
  {
    "crush": "",
    "damage": "1413",
    "gif": "",
    "id": "Jack-8-b+3,2",
    "image": "",
    "input": "b+3,2",
    "name": "",
    "notes": "* Transition to GMH with D\n** (+0 oB, +5 oH)",
    "on_block": "-4",
    "on_ch": "",
    "on_hit": "+1",
    "recovery": "",
    "short_notes": "* Transition to GMH with D\n** (+0 oB, +5 oH)",
    "startup": "i22",
    "tags": "",
    "target": "m,h",
    "video": ""
  },
  {
    "crush": "",
    "damage": "141320",
    "gif": "",
    "id": "Jack-8-b+3,2,2",
    "image": "",
    "input": "b+3,2,2",
    "name": "Mad Dozer",
    "notes": "* Balcony Break\n* Can be charged to power up",
    "on_block": "-9",
    "on_ch": "",
    "on_hit": "+44d (-14)",
    "recovery": "",
    "short_notes": "* Can be charged to power up",
    "startup": "i25",
    "tags": "bbr",
    "target": "m,h,h",
    "video": ""
  },
  {
    "crush": "",
    "damage": "141340",
    "gif": "",
    "id": "Jack-8-b+3,2,2*",
    "image": "",
    "input": "b+3,2,2*",
    "name": "Mad Dozer (charged)",
    "notes": "* Balcony Break\n* Wall Crush +3 on block\n\n\n* Chip damage on block",
    "on_block": "-9",
    "on_ch": "",
    "on_hit": "+13d (+5)",
    "recovery": "",
    "short_notes": "\n",
    "startup": "i67",
    "tags": "bbr wc chp",
    "target": "m,h,m",
    "video": ""
  },
  {
    "crush": "",
    "damage": "16",
    "gif": "",
    "id": "Jack-8-b+4",
    "image": "",
    "input": "b+4",
    "name": "",
    "notes": "*",
    "on_block": "-13",
    "on_ch": "-2a",
    "on_hit": "-2",
    "recovery": "",
    "short_notes": "*",
    "startup": "i13",
    "tags": "",
    "target": "m",
    "video": ""
  },
  {
    "crush": "",
    "damage": "1621",
    "gif": "",
    "id": "Jack-8-b+4,4",
    "image": "",
    "input": "b+4,4",
    "name": "Sherman Stomp",
    "notes": "* Combos from 1st hit CH\n* When comboing from 1st hit: \nFloor Break",
    "on_block": "-4",
    "on_ch": "",
    "on_hit": "-8d",
    "recovery": "",
    "short_notes": "* Combos from 1st hit CH\n* When comboing from 1st hit: ",
    "startup": "i30",
    "tags": "fbr",
    "target": "m,m",
    "video": ""
  },
  {
    "crush": "",
    "damage": "28",
    "gif": "",
    "id": "Jack-8-b+1+2",
    "image": "",
    "input": "b+1+2",
    "name": "Tyulpan Blast",
    "notes": "* Heat Engager\n\n* Heat Dash +5, +43d(+35)\n\n* Balcony Break",
    "on_block": "-19",
    "on_ch": "",
    "on_hit": "-1d (-10)",
    "recovery": "",
    "short_notes": "\n* Heat Dash +5, +43d(+35)\n",
    "startup": "i14",
    "tags": "he bbr",
    "target": "m",
    "video": ""
  },
  {
    "crush": "pc",
    "damage": "30",
    "gif": "",
    "id": "Jack-8-ub+1+2",
    "image": "",
    "input": "ub+1+2",
    "name": "Barrel Jacket Hammer",
    "notes": "* Balcony Break\n* Homing\n* Chip damage on block\nPower crush",
    "on_block": "-9",
    "on_ch": "",
    "on_hit": "+23",
    "recovery": "",
    "short_notes": "",
    "startup": "i20",
    "tags": "bbr hom chp pc",
    "target": "h",
    "video": ""
  },
  {
    "crush": "js",
    "damage": "25",
    "gif": "",
    "id": "Jack-8-u+4",
    "image": "",
    "input": "u+4",
    "name": "",
    "notes": "* Balcony Break\n* Alternate input ub+4, uf+4\nLow crush",
    "on_block": "-16",
    "on_ch": "",
    "on_hit": "+15a (+5)",
    "recovery": "",
    "short_notes": "* Alternate input ub+4, uf+4",
    "startup": "i25",
    "tags": "bbr js",
    "target": "m",
    "video": ""
  },
  {
    "crush": "",
    "damage": "23",
    "gif": "",
    "id": "Jack-8-u+1+2",
    "image": "",
    "input": "u+1+2",
    "name": "Patriot Fist",
    "notes": "*",
    "on_block": "-13",
    "on_ch": "",
    "on_hit": "+49a (+39)",
    "recovery": "",
    "short_notes": "*",
    "startup": "i19",
    "tags": "",
    "target": "m",
    "video": ""
  },
  {
    "crush": "js",
    "damage": "40",
    "gif": "",
    "id": "Jack-8-u+3+4",
    "image": "",
    "input": "u+3+4",
    "name": "Giant Foot Stomp",
    "notes": "* Unblockable\n* Can input additional 3+4 (up to 4 times) to fly farther and deal more damage\n* Alternate input ub+3+4\nLow crush",
    "on_block": "!",
    "on_ch": "",
    "on_hit": "+17d",
    "recovery": "",
    "short_notes": "* Unblockable\n* Can input additional 3+4 (up to 4 times) to fly farther and deal more damage\n* Alternate input ub+3+4",
    "startup": "i94~100",
    "tags": "js",
    "target": "m",
    "video": ""
  },
  {
    "crush": "",
    "damage": "10",
    "gif": "",
    "id": "Jack-8-uf+1",
    "image": "",
    "input": "uf+1",
    "name": "Sky Sweeper",
    "notes": "* Tornado\n* Only hits airborne opponents\n* Transition to GMH with D\n** (+75a (+59))\n* Can be charged to power up\n* Alternate input ub+1, u+1",
    "on_block": "",
    "on_ch": "",
    "on_hit": "+71a (+55)",
    "recovery": "",
    "short_notes": "* Only hits airborne opponents\n* Transition to GMH with D\n** (+75a (+59))\n* Can be charged to power up\n* Alternate input ub+1, u+1",
    "startup": "i17",
    "tags": "trn",
    "target": "h",
    "video": ""
  },
  {
    "crush": "",
    "damage": "35",
    "gif": "",
    "id": "Jack-8-uf+1*",
    "image": "",
    "input": "uf+1*",
    "name": "Sky Sweeper (charged)",
    "notes": "* Tornado\n* Only hits airborne opponents\n* Transition to GMH with D\n** (+70a (+54))\n* Alternate input ub+1*, u+1*",
    "on_block": "",
    "on_ch": "",
    "on_hit": "+69a (+53)",
    "recovery": "",
    "short_notes": "* Only hits airborne opponents\n* Transition to GMH with D\n** (+70a (+54))\n* Alternate input ub+1*, u+1*",
    "startup": "i35",
    "tags": "trn",
    "target": "h",
    "video": ""
  },
  {
    "crush": "js",
    "damage": "25",
    "gif": "",
    "id": "Jack-8-uf+2",
    "image": "",
    "input": "uf+2",
    "name": "Reactor Elbow",
    "notes": "* Elbow\nLow crush",
    "on_block": "+4c",
    "on_ch": "+11d",
    "on_hit": "+7c",
    "recovery": "",
    "short_notes": "",
    "startup": "i24",
    "tags": "elb js",
    "target": "m",
    "video": ""
  },
  {
    "crush": "js",
    "damage": "6",
    "gif": "",
    "id": "Jack-8-uf+3",
    "image": "",
    "input": "uf+3",
    "name": "Terrapulser",
    "notes": "* Automatically transitions to GMH on hit or block\n* Alternate input ub+3, u+3\nLow crush",
    "on_block": "-17",
    "on_ch": "",
    "on_hit": "+8c",
    "recovery": "",
    "short_notes": "* Automatically transitions to GMH on hit or block\n* Alternate input ub+3, u+3",
    "startup": "i23",
    "tags": "js",
    "target": "l",
    "video": ""
  },
  {
    "crush": "js",
    "damage": "23",
    "gif": "",
    "id": "Jack-8-uf+3+4",
    "image": "",
    "input": "uf+3+4",
    "name": "Pancake Press",
    "notes": "* Automatically transitions to SIT on hit or block\nLow crush",
    "on_block": "+13cg",
    "on_ch": "",
    "on_hit": "+20d",
    "recovery": "",
    "short_notes": "* Automatically transitions to SIT on hit or block",
    "startup": "i34",
    "tags": "js",
    "target": "m",
    "video": ""
  },
  {
    "crush": "",
    "damage": "22",
    "gif": "",
    "id": "Jack-8-f,F+1",
    "image": "",
    "input": "f,F+1",
    "name": "Jackhammer",
    "notes": "* Transition to GMH with D\n* (+4c oB, +8c oH)",
    "on_block": "-6",
    "on_ch": "+16d",
    "on_hit": "+8c",
    "recovery": "",
    "short_notes": "* Transition to GMH with D\n* (+4c oB, +8c oH)",
    "startup": "i15",
    "tags": "",
    "target": "m",
    "video": ""
  },
  {
    "crush": "",
    "damage": "23",
    "gif": "",
    "id": "Jack-8-f,F+2",
    "image": "",
    "input": "f,F+2",
    "name": "Rocket Uppercut",
    "notes": "* Can be charged to power up",
    "on_block": "-16",
    "on_ch": "",
    "on_hit": "+53a (+43)",
    "recovery": "",
    "short_notes": "* Can be charged to power up",
    "startup": "i18",
    "tags": "",
    "target": "m",
    "video": ""
  },
  {
    "crush": "",
    "damage": "35",
    "gif": "",
    "id": "Jack-8-f,F+2*",
    "image": "",
    "input": "f,F+2*",
    "name": "Rocket Uppercut (charged)",
    "notes": "* Tornado\n* Chip damage on block",
    "on_block": "-15",
    "on_ch": "",
    "on_hit": "+61a",
    "recovery": "",
    "short_notes": "",
    "startup": "34",
    "tags": "trn chp",
    "target": "m",
    "video": ""
  },
  {
    "crush": "",
    "damage": "22",
    "gif": "",
    "id": "Jack-8-f,F+3",
    "image": "",
    "input": "f,F+3",
    "name": "Granite Stomping",
    "notes": "* Transition to FC with D",
    "on_block": "+4c",
    "on_ch": "+22a",
    "on_hit": "+9c",
    "recovery": "",
    "short_notes": "* Transition to FC with D",
    "startup": "i26",
    "tags": "",
    "target": "m",
    "video": ""
  },
  {
    "crush": "",
    "damage": "32",
    "gif": "",
    "id": "Jack-8-f,F+4",
    "image": "",
    "input": "f,F+4",
    "name": "Rocket Kick",
    "notes": "* Tornado \n* Balcony Break\n* Chip damage on block",
    "on_block": "-10",
    "on_ch": "",
    "on_hit": "+15d (+5)",
    "recovery": "",
    "short_notes": "",
    "startup": "i16",
    "tags": "trn bbr chp",
    "target": "m",
    "video": ""
  },
  {
    "crush": "",
    "damage": "20",
    "gif": "",
    "id": "Jack-8-f,F+1+2",
    "image": "",
    "input": "f,F+1+2",
    "name": "",
    "notes": "*\nHoming",
    "on_block": "-15",
    "on_ch": "",
    "on_hit": "+22cs",
    "recovery": "",
    "short_notes": "*",
    "startup": "i15",
    "tags": "hom",
    "target": "m",
    "video": ""
  },
  {
    "crush": "",
    "damage": "20,24",
    "gif": "",
    "id": "Jack-8-f,F+1+2,2",
    "image": "",
    "input": "f,F+1+2,2",
    "name": "Cross Cut Blast",
    "notes": "*\nBalcony Break\n* Combos from 1st hit",
    "on_block": "-11",
    "on_ch": "",
    "on_hit": "+11a (+2)",
    "recovery": "",
    "short_notes": "*\n* Combos from 1st hit",
    "startup": "i32",
    "tags": "bbr",
    "target": "m,m",
    "video": ""
  },
  {
    "crush": "cs",
    "damage": "20,21",
    "gif": "",
    "id": "Jack-8-f,F+1+2,1+2",
    "image": "",
    "input": "f,F+1+2,1+2",
    "name": "High and Low Cross Cut",
    "notes": "* Alternate input FC.d+1+2\nHigh crush",
    "on_block": "-19",
    "on_ch": "",
    "on_hit": "+13d",
    "recovery": "",
    "short_notes": "* Alternate input FC.d+1+2",
    "startup": "i28",
    "tags": "cs",
    "target": "m,l",
    "video": ""
  },
  {
    "crush": "js",
    "damage": "25",
    "gif": "",
    "id": "Jack-8-f,F+1+4",
    "image": "",
    "input": "f,F+1+4",
    "name": "Sliding Attack",
    "notes": "* Low attack on landing\nLow crush",
    "on_block": "-82",
    "on_ch": "",
    "on_hit": "-88",
    "recovery": "",
    "short_notes": "* Low attack on landing",
    "startup": "i21",
    "tags": "js",
    "target": "m (l)",
    "video": ""
  },
  {
    "crush": "",
    "damage": "25",
    "gif": "",
    "id": "Jack-8-f,f,F+2",
    "image": "",
    "input": "f,f,F+2",
    "name": "Cemaho Chop",
    "notes": "* Chip damage on block\n* Alternate input wr2",
    "on_block": "+10",
    "on_ch": "",
    "on_hit": "+6",
    "recovery": "",
    "short_notes": "* Alternate input wr2",
    "startup": "i22",
    "tags": "chp",
    "target": "m",
    "video": ""
  },
  {
    "crush": "",
    "damage": "34",
    "gif": "",
    "id": "Jack-8-f,f,F+1+2",
    "image": "",
    "input": "f,f,F+1+2",
    "name": "Mimesis Charging Tackle",
    "notes": "* Balcony Break\n* Chip damage on block\n* Alternate input wr1+2",
    "on_block": "+3",
    "on_ch": "",
    "on_hit": "+7a (-2)",
    "recovery": "",
    "short_notes": "* Alternate input wr1+2",
    "startup": "i20",
    "tags": "bbr chp",
    "target": "m",
    "video": ""
  },
  {
    "crush": "",
    "damage": "14",
    "gif": "",
    "id": "Jack-8-ws1",
    "image": "",
    "input": "ws1",
    "name": "Killing Uppercut",
    "notes": "*",
    "on_block": "-13",
    "on_ch": "",
    "on_hit": "+34a (+24)",
    "recovery": "",
    "short_notes": "*",
    "startup": "i15",
    "tags": "",
    "target": "m",
    "video": ""
  },
  {
    "crush": "",
    "damage": "10",
    "gif": "",
    "id": "Jack-8-ws2",
    "image": "",
    "input": "ws2",
    "name": "",
    "notes": "*",
    "on_block": "-7",
    "on_ch": "",
    "on_hit": "+4",
    "recovery": "",
    "short_notes": "*",
    "startup": "i14",
    "tags": "",
    "target": "m",
    "video": ""
  },
  {
    "crush": "",
    "damage": "10,17",
    "gif": "",
    "id": "Jack-8-ws2,1",
    "image": "",
    "input": "ws2,1",
    "name": "V-Twin",
    "notes": "* Combos from 1st hit",
    "on_block": "-14c",
    "on_ch": "+49a",
    "on_hit": "+3d",
    "recovery": "",
    "short_notes": "* Combos from 1st hit",
    "startup": "i15",
    "tags": "",
    "target": "m,m",
    "video": ""
  },
  {
    "crush": "",
    "damage": "10,26",
    "gif": "",
    "id": "Jack-8-ws2,4",
    "image": "",
    "input": "ws2,4",
    "name": "V-Deathblow",
    "notes": "* Balcony Break\n* Combos from 1st hit",
    "on_block": "+3",
    "on_ch": "",
    "on_hit": "+21a (+11)",
    "recovery": "",
    "short_notes": "* Combos from 1st hit",
    "startup": "i16",
    "tags": "bbr",
    "target": "m,h",
    "video": ""
  },
  {
    "crush": "",
    "damage": "18",
    "gif": "",
    "id": "Jack-8-ws3",
    "image": "",
    "input": "ws3",
    "name": "",
    "notes": "* Knee\n* Transition to GMH with D\n** (+2 oB, +16g oH)\n* Alternate input f+3",
    "on_block": "-9",
    "on_ch": "",
    "on_hit": "+5",
    "recovery": "",
    "short_notes": "* Transition to GMH with D\n** (+2 oB, +16g oH)\n* Alternate input f+3",
    "startup": "i15",
    "tags": "kne",
    "target": "m",
    "video": ""
  },
  {
    "crush": "",
    "damage": "18,20",
    "gif": "",
    "id": "Jack-8-ws3,2",
    "image": "",
    "input": "ws3,2",
    "name": "Two-Step Die",
    "notes": "* Balcony Break\n* Combos from 1st hit\n* Alternate input f+3,2",
    "on_block": "-9",
    "on_ch": "",
    "on_hit": "+44d (-14)",
    "recovery": "",
    "short_notes": "* Combos from 1st hit\n* Alternate input f+3,2",
    "startup": "i23",
    "tags": "bbr",
    "target": "m,h",
    "video": ""
  },
  {
    "crush": "",
    "damage": "18,20",
    "gif": "",
    "id": "Jack-8-ws3,1+2",
    "image": "",
    "input": "ws3,1+2",
    "name": "Machine Press",
    "notes": "* Combos from 1st hit CH\n* Alternate input f+3,1+2",
    "on_block": "-11c",
    "on_ch": "+48a",
    "on_hit": "+2d",
    "recovery": "",
    "short_notes": "* Combos from 1st hit CH\n* Alternate input f+3,1+2",
    "startup": "i25",
    "tags": "",
    "target": "m,m",
    "video": ""
  },
  {
    "crush": "",
    "damage": "20",
    "gif": "",
    "id": "Jack-8-ws4",
    "image": "",
    "input": "ws4",
    "name": "Toe Smash",
    "notes": "*",
    "on_block": "-6",
    "on_ch": "",
    "on_hit": "+5",
    "recovery": "",
    "short_notes": "*",
    "startup": "i11",
    "tags": "",
    "target": "m",
    "video": ""
  },
  {
    "crush": "",
    "damage": "14",
    "gif": "",
    "id": "Jack-8-ws1+2",
    "image": "",
    "input": "ws1+2",
    "name": "",
    "notes": "*",
    "on_block": "-15",
    "on_ch": "",
    "on_hit": "+26a (+16)",
    "recovery": "",
    "short_notes": "*",
    "startup": "i20",
    "tags": "",
    "target": "m",
    "video": ""
  },
  {
    "crush": "",
    "damage": "14,12",
    "gif": "",
    "id": "Jack-8-ws1+2,1+2",
    "image": "",
    "input": "ws1+2,1+2",
    "name": "",
    "notes": "* Floor Break\n* Combos from 1st hit",
    "on_block": "-15",
    "on_ch": "",
    "on_hit": "+15d",
    "recovery": "",
    "short_notes": "* Combos from 1st hit",
    "startup": "i17",
    "tags": "fbr",
    "target": "m,m",
    "video": ""
  },
  {
    "crush": "",
    "damage": "14,12,14",
    "gif": "",
    "id": "Jack-8-ws1+2,1+2,1+2",
    "image": "",
    "input": "ws1+2,1+2,1+2",
    "name": "Double Hammer Thrash",
    "notes": "* Balcony Break\n* Combos from 1st hit",
    "on_block": "-23",
    "on_ch": "",
    "on_hit": "+6d",
    "recovery": "",
    "short_notes": "* Combos from 1st hit",
    "startup": "i27",
    "tags": "bbr",
    "target": "m,m,l",
    "video": ""
  },
  {
    "crush": "",
    "damage": "23",
    "gif": "",
    "id": "Jack-8-ss1",
    "image": "",
    "input": "ss1",
    "name": "Discharger",
    "notes": "",
    "on_block": "+6c",
    "on_ch": "",
    "on_hit": "+59a",
    "recovery": "",
    "short_notes": "",
    "startup": "i32",
    "tags": "",
    "target": "m",
    "video": ""
  },
  {
    "crush": "",
    "damage": "20",
    "gif": "",
    "id": "Jack-8-ss2",
    "image": "",
    "input": "ss2",
    "name": "Piston Gun Snipe",
    "notes": "* Balcony Break\n* Transition to GMH with D\n** (+9 oB, +35d (+27) oH)",
    "on_block": "+9",
    "on_ch": "",
    "on_hit": "+35d (+27)",
    "recovery": "",
    "short_notes": "* Transition to GMH with D\n** (+9 oB, +35d (+27) oH)",
    "startup": "i17",
    "tags": "bbr",
    "target": "h",
    "video": ""
  },
  {
    "crush": "cs",
    "damage": "10",
    "gif": "",
    "id": "Jack-8-FC.1",
    "image": "",
    "input": "FC.1",
    "name": "",
    "notes": "*\nHigh crush",
    "on_block": "-8",
    "on_ch": "",
    "on_hit": "+3",
    "recovery": "rFC",
    "short_notes": "*",
    "startup": "i19",
    "tags": "cs",
    "target": "l",
    "video": ""
  },
  {
    "crush": "cs",
    "damage": "10,14",
    "gif": "",
    "id": "Jack-8-FC.1,1",
    "image": "",
    "input": "FC.1,1",
    "name": "Double Low Hammer",
    "notes": "*\nHigh crush",
    "on_block": "-12",
    "on_ch": "",
    "on_hit": "+5",
    "recovery": "rFC",
    "short_notes": "*",
    "startup": "i31",
    "tags": "cs",
    "target": "l,l",
    "video": ""
  },
  {
    "crush": "",
    "damage": "10,24",
    "gif": "",
    "id": "Jack-8-FC.1,2",
    "image": "",
    "input": "FC.1,2",
    "name": "Megaton Strike",
    "notes": "* Balcony Break",
    "on_block": "-11",
    "on_ch": "+43a (-4)",
    "on_hit": "+11a (+2)",
    "recovery": "rFC",
    "short_notes": "",
    "startup": "i32",
    "tags": "bbr",
    "target": "l,m",
    "video": ""
  },
  {
    "crush": "cs",
    "damage": "8",
    "gif": "",
    "id": "Jack-8-FC.2",
    "image": "",
    "input": "FC.2",
    "name": "",
    "notes": "* Alternate input d+2\nHigh crush",
    "on_block": "-4",
    "on_ch": "",
    "on_hit": "+7",
    "recovery": "rFC",
    "short_notes": "* Alternate input d+2",
    "startup": "i11",
    "tags": "cs",
    "target": "s",
    "video": ""
  },
  {
    "crush": "cs",
    "damage": "12",
    "gif": "",
    "id": "Jack-8-FC.3",
    "image": "",
    "input": "FC.3",
    "name": "",
    "notes": "* Alternate input d+3\nHigh crush",
    "on_block": "-17",
    "on_ch": "",
    "on_hit": "-6",
    "recovery": "rFC",
    "short_notes": "* Alternate input d+3",
    "startup": "i20",
    "tags": "cs",
    "target": "l",
    "video": ""
  },
  {
    "crush": "cs",
    "damage": "10",
    "gif": "",
    "id": "Jack-8-FC.4",
    "image": "",
    "input": "FC.4",
    "name": "",
    "notes": "* Alternate input d+4\nHigh crush",
    "on_block": "-15",
    "on_ch": "",
    "on_hit": "-4",
    "recovery": "rFC",
    "short_notes": "* Alternate input d+4",
    "startup": "i16",
    "tags": "cs",
    "target": "l",
    "video": ""
  },
  {
    "crush": "cs",
    "damage": "21",
    "gif": "",
    "id": "Jack-8-FC.1+2",
    "image": "",
    "input": "FC.1+2",
    "name": "",
    "notes": "* Alternate input FC.db+1+2\nHigh crush",
    "on_block": "-15",
    "on_ch": "",
    "on_hit": "+13d",
    "recovery": "rFC",
    "short_notes": "* Alternate input FC.db+1+2",
    "startup": "i24",
    "tags": "cs",
    "target": "l",
    "video": ""
  },
  {
    "crush": "",
    "damage": "2123",
    "gif": "",
    "id": "Jack-8-FC.1+2,1+2",
    "image": "",
    "input": "FC.1+2,1+2",
    "name": "Low Cross Combo",
    "notes": "* Combos from 1st hit",
    "on_block": "-18",
    "on_ch": "",
    "on_hit": "+42a (+32)",
    "recovery": "",
    "short_notes": "* Combos from 1st hit",
    "startup": "i40",
    "tags": "",
    "target": "l,m",
    "video": ""
  },
  {
    "crush": "cs",
    "damage": "14",
    "gif": "",
    "id": "Jack-8-FC.db+1",
    "image": "",
    "input": "FC.db+1",
    "name": "",
    "notes": "*\nHigh crush",
    "on_block": "-11",
    "on_ch": "",
    "on_hit": "+3",
    "recovery": "rFC",
    "short_notes": "*",
    "startup": "i14",
    "tags": "cs",
    "target": "l",
    "video": ""
  },
  {
    "crush": "cs",
    "damage": "14,10",
    "gif": "",
    "id": "Jack-8-FC.db+1,1",
    "image": "",
    "input": "FC.db+1,1",
    "name": "",
    "notes": "*\nHigh crush",
    "on_block": "-6",
    "on_ch": "",
    "on_hit": "+5",
    "recovery": "rFC",
    "short_notes": "*",
    "startup": "i24",
    "tags": "cs",
    "target": "l,m",
    "video": ""
  },
  {
    "crush": "",
    "damage": "14,10,20",
    "gif": "",
    "id": "Jack-8-FC.db+1,1,1",
    "image": "",
    "input": "FC.db+1,1,1",
    "name": "Pulverizer",
    "notes": "* Balcony Break\n* Can be charged to power up",
    "on_block": "-14",
    "on_ch": "",
    "on_hit": "+9a",
    "recovery": "",
    "short_notes": "* Can be charged to power up",
    "startup": "i20",
    "tags": "bbr",
    "target": "l,m,m",
    "video": ""
  },
  {
    "crush": "",
    "damage": "14,10,30",
    "gif": "",
    "id": "Jack-8-FC.db+1,1,1*",
    "image": "",
    "input": "FC.db+1,1,1*",
    "name": "Pulverizer (charged)",
    "notes": "* Balcony Break\n* Chip damage on block",
    "on_block": "-6",
    "on_ch": "",
    "on_hit": "+15a (+7)",
    "recovery": "",
    "short_notes": "",
    "startup": "i34",
    "tags": "bbr chp",
    "target": "l,m,m",
    "video": ""
  },
  {
    "crush": "",
    "damage": "5",
    "gif": "",
    "id": "Jack-8-FC.df+1",
    "image": "",
    "input": "FC.df+1",
    "name": "",
    "notes": "*",
    "on_block": "-21",
    "on_ch": "",
    "on_hit": "-11c",
    "recovery": "",
    "short_notes": "*",
    "startup": "i23",
    "tags": "",
    "target": "m",
    "video": ""
  },
  {
    "crush": "",
    "damage": "5,8",
    "gif": "",
    "id": "Jack-8-FC.df+1,2",
    "image": "",
    "input": "FC.df+1,2",
    "name": "",
    "notes": "* Combos from 1st hit",
    "on_block": "-21",
    "on_ch": "",
    "on_hit": "-11c",
    "recovery": "",
    "short_notes": "* Combos from 1st hit",
    "startup": "i16",
    "tags": "",
    "target": "m,m",
    "video": ""
  },
  {
    "crush": "",
    "damage": "5,8,11",
    "gif": "",
    "id": "Jack-8-FC.df+1,2,1",
    "image": "",
    "input": "FC.df+1,2,1",
    "name": "",
    "notes": "* Combos from 1st hit",
    "on_block": "-11",
    "on_ch": "",
    "on_hit": "+16cs",
    "recovery": "",
    "short_notes": "* Combos from 1st hit",
    "startup": "i16",
    "tags": "",
    "target": "m,m,m",
    "video": ""
  },
  {
    "crush": "",
    "damage": "5,8,11,30",
    "gif": "",
    "id": "Jack-8-FC.df+1,2,1,1",
    "image": "",
    "input": "FC.df+1,2,1,1",
    "name": "Windmill Punches",
    "notes": "* Guard Break",
    "on_block": "+15",
    "on_ch": "",
    "on_hit": "+13BT",
    "recovery": "",
    "short_notes": "* Guard Break",
    "startup": "i21",
    "tags": "",
    "target": "m,m,m,h",
    "video": ""
  },
  {
    "crush": "cs",
    "damage": "12",
    "gif": "",
    "id": "Jack-8-FC.df+2",
    "image": "",
    "input": "FC.df+2",
    "name": "",
    "notes": "*\nHigh crush",
    "on_block": "-13",
    "on_ch": "",
    "on_hit": "-2",
    "recovery": "rFC",
    "short_notes": "*",
    "startup": "i17",
    "tags": "cs",
    "target": "m",
    "video": ""
  },
  {
    "crush": "cs",
    "damage": "12,10",
    "gif": "",
    "id": "Jack-8-FC.df+2,1",
    "image": "",
    "input": "FC.df+2,1",
    "name": "",
    "notes": "*\nHigh crush",
    "on_block": "-13",
    "on_ch": "",
    "on_hit": "+7",
    "recovery": "rFC",
    "short_notes": "*",
    "startup": "i26",
    "tags": "cs",
    "target": "m,m",
    "video": ""
  },
  {
    "crush": "cs",
    "damage": "12,10,10",
    "gif": "",
    "id": "Jack-8-FC.df+2,1,2",
    "image": "",
    "input": "FC.df+2,1,2",
    "name": "Swing R Knuckle",
    "notes": "*\nHigh crush",
    "on_block": "-12",
    "on_ch": "",
    "on_hit": "+29a (+19)",
    "recovery": "rFC",
    "short_notes": "*",
    "startup": "i27",
    "tags": "cs",
    "target": "m,m,m",
    "video": ""
  },
  {
    "crush": "cs",
    "damage": "12,8",
    "gif": "",
    "id": "Jack-8-FC.df+2,d+1",
    "image": "",
    "input": "FC.df+2,d+1",
    "name": "Swing R Knuckle Low",
    "notes": "* Balcony Break\n* Combos from 1st hit\nHigh crush",
    "on_block": "-11",
    "on_ch": "",
    "on_hit": "+0",
    "recovery": "rFC",
    "short_notes": "* Combos from 1st hit",
    "startup": "i22",
    "tags": "bbr cs",
    "target": "m,l",
    "video": ""
  },
  {
    "crush": "cs",
    "damage": "12,23",
    "gif": "",
    "id": "Jack-8-FC.df+2,f+1",
    "image": "",
    "input": "FC.df+2,f+1",
    "name": "Swing R Knuckle High",
    "notes": "* Balcony Break\n* Combos from 1st hit\nHigh crush",
    "on_block": "-13",
    "on_ch": "",
    "on_hit": "+32a",
    "recovery": "rFC",
    "short_notes": "* Combos from 1st hit",
    "startup": "i19",
    "tags": "bbr cs",
    "target": "m,h",
    "video": ""
  },
  {
    "crush": "",
    "damage": "10",
    "gif": "",
    "id": "Jack-8-FC.df+4",
    "image": "",
    "input": "FC.df+4",
    "name": "",
    "notes": "*",
    "on_block": "-12",
    "on_ch": "",
    "on_hit": "+4",
    "recovery": "",
    "short_notes": "*",
    "startup": "i12",
    "tags": "",
    "target": "m",
    "video": ""
  },
  {
    "crush": "",
    "damage": "10,17",
    "gif": "",
    "id": "Jack-8-FC.df+4,2",
    "image": "",
    "input": "FC.df+4,2",
    "name": "Mimesis Spike Press",
    "notes": "*",
    "on_block": "-14",
    "on_ch": "+19d",
    "on_hit": "+4c",
    "recovery": "",
    "short_notes": "*",
    "startup": "i20",
    "tags": "",
    "target": "m,m",
    "video": ""
  },
  {
    "crush": "",
    "damage": "28",
    "gif": "",
    "id": "Jack-8-FC.df+3+4",
    "image": "",
    "input": "FC.df+3+4",
    "name": "Atomic Shoulder Tackle",
    "notes": "* Balcony Break",
    "on_block": "-9",
    "on_ch": "+33a (-14)",
    "on_hit": "+1a (-8)",
    "recovery": "",
    "short_notes": "",
    "startup": "i21",
    "tags": "bbr",
    "target": "m",
    "video": ""
  },
  {
    "crush": "",
    "damage": "22",
    "gif": "",
    "id": "Jack-8-GMC.1",
    "image": "",
    "input": "GMC.1",
    "name": "Jaguar Hook - Gamma",
    "notes": "* Homing\n* * Partially uses remaining Heat time\n* Chip damage on block",
    "on_block": "-6",
    "on_ch": "",
    "on_hit": "+73a (+57)",
    "recovery": "",
    "short_notes": "* * Partially uses remaining Heat time",
    "startup": "i22",
    "tags": "hom chp",
    "target": "m",
    "video": ""
  },
  {
    "crush": "pc",
    "damage": "22",
    "gif": "",
    "id": "Jack-8-GMC.2",
    "image": "",
    "input": "GMC.2",
    "name": "Exaton Blast - Gamma",
    "notes": "* Tornado\n* Guard Break\n* Balcony Break\n* Partially uses remaining Heat time\n* Chip damage on block\nPower crush",
    "on_block": "+11",
    "on_ch": "",
    "on_hit": "+31a (+5)",
    "recovery": "",
    "short_notes": "* Guard Break\n* Partially uses remaining Heat time",
    "startup": "i20",
    "tags": "trn bbr chp pc",
    "target": "h",
    "video": ""
  },
  {
    "crush": "",
    "damage": "20",
    "gif": "",
    "id": "Jack-8-GMH.1",
    "image": "",
    "input": "GMH.1",
    "name": "Juggernaut Hook",
    "notes": "* Homing\n* Balcony Break",
    "on_block": "-9",
    "on_ch": "",
    "on_hit": "+25d",
    "recovery": "",
    "short_notes": "",
    "startup": "i22",
    "tags": "hom bbr",
    "target": "m",
    "video": ""
  },
  {
    "crush": "",
    "damage": "40",
    "gif": "",
    "id": "Jack-8-GMH.2",
    "image": "",
    "input": "GMH.2",
    "name": "Exaton Blast",
    "notes": "* Balcony Break\n* Tornado",
    "on_block": "+11",
    "on_ch": "",
    "on_hit": "+21d (+11)",
    "recovery": "",
    "short_notes": "",
    "startup": "i20",
    "tags": "bbr trn",
    "target": "h",
    "video": ""
  },
  {
    "crush": "",
    "damage": "28",
    "gif": "",
    "id": "Jack-8-GMH.3",
    "image": "",
    "input": "GMH.3",
    "name": "Granite Stomp",
    "notes": "* Transition to FC with D\n** (+7 oH)",
    "on_block": "+4",
    "on_ch": "+22a",
    "on_hit": "+9c",
    "recovery": "",
    "short_notes": "* Transition to FC with D\n** (+7 oH)",
    "startup": "i24",
    "tags": "",
    "target": "m",
    "video": ""
  },
  {
    "crush": "",
    "damage": "30",
    "gif": "",
    "id": "Jack-8-GMH.4",
    "image": "",
    "input": "GMH.4",
    "name": "Full Metal Deathblow",
    "notes": "* Heat Engager\n\n* Heat Dash +5, +36a(+26)\n\n* Balcony Break\n* Chip damage on block",
    "on_block": "+3",
    "on_ch": "",
    "on_hit": "+21d (+11)",
    "recovery": "",
    "short_notes": "\n* Heat Dash +5, +36a(+26)\n",
    "startup": "i14",
    "tags": "he bbr chp",
    "target": "h",
    "video": ""
  },
  {
    "crush": "pc",
    "damage": "20",
    "gif": "",
    "id": "Jack-8-GMH.3+4",
    "image": "",
    "input": "GMH.3+4",
    "name": "Particle Barrier",
    "notes": "* Heat Engager\n\n* Heat Dash +5, +36a(+26)\n\n* Chip damage on block when absorbing an attack\nPower crush",
    "on_block": "-13",
    "on_ch": "",
    "on_hit": "+40d (-18)",
    "recovery": "",
    "short_notes": "\n* Heat Dash +5, +36a(+26)\n",
    "startup": "i20",
    "tags": "he chp pc",
    "target": "sm",
    "video": ""
  },
  {
    "crush": "",
    "damage": "26",
    "gif": "",
    "id": "Jack-8-GMH.f+1",
    "image": "",
    "input": "GMH.f+1",
    "name": "Prime Windup Uppercut",
    "notes": "* Tornado\n* Instant Tornado",
    "on_block": "-17",
    "on_ch": "",
    "on_hit": "+66a (+50)",
    "recovery": "",
    "short_notes": "* Instant Tornado",
    "startup": "i20",
    "tags": "trn",
    "target": "m",
    "video": ""
  },
  {
    "crush": "pc",
    "damage": "34",
    "gif": "",
    "id": "Jack-8-GMH.f+2",
    "image": "",
    "input": "GMH.f+2",
    "name": "Megalodriller",
    "notes": "* Balcony Break\nPower crush",
    "on_block": "-13",
    "on_ch": "",
    "on_hit": "+30a (+4)",
    "recovery": "",
    "short_notes": "",
    "startup": "i29",
    "tags": "bbr pc",
    "target": "m",
    "video": ""
  },
  {
    "crush": "js",
    "damage": "",
    "gif": "",
    "id": "Jack-8-GMH.ub",
    "image": "",
    "input": "GMH.ub",
    "name": "Breakout Fortress",
    "notes": "*\nLow crush",
    "on_block": "",
    "on_ch": "",
    "on_hit": "",
    "recovery": "",
    "short_notes": "*",
    "startup": "",
    "tags": "js",
    "target": "",
    "video": ""
  },
  {
    "crush": "js",
    "damage": "",
    "gif": "",
    "id": "Jack-8-GMH.uf",
    "image": "",
    "input": "GMH.uf",
    "name": "Flying Fortress",
    "notes": "*\nLow crush",
    "on_block": "",
    "on_ch": "",
    "on_hit": "",
    "recovery": "",
    "short_notes": "*",
    "startup": "",
    "tags": "js",
    "target": "",
    "video": ""
  },
  {
    "crush": "",
    "damage": "10",
    "gif": "",
    "id": "Jack-8-SIT.1",
    "image": "",
    "input": "SIT.1",
    "name": "",
    "notes": "*",
    "on_block": "-48",
    "on_ch": "",
    "on_hit": "-37",
    "recovery": "SIT",
    "short_notes": "*",
    "startup": "i19",
    "tags": "",
    "target": "l",
    "video": ""
  },
  {
    "crush": "",
    "damage": "1010",
    "gif": "",
    "id": "Jack-8-SIT.1,2",
    "image": "",
    "input": "SIT.1,2",
    "name": "",
    "notes": "* Combos from 1st hit",
    "on_block": "-47",
    "on_ch": "",
    "on_hit": "-36",
    "recovery": "SIT",
    "short_notes": "* Combos from 1st hit",
    "startup": "i15",
    "tags": "",
    "target": "l,l",
    "video": ""
  },
  {
    "crush": "",
    "damage": "101010",
    "gif": "",
    "id": "Jack-8-SIT.1,2,1",
    "image": "",
    "input": "SIT.1,2,1",
    "name": "",
    "notes": "* Combos from 1st hit",
    "on_block": "-47",
    "on_ch": "",
    "on_hit": "-36",
    "recovery": "SIT",
    "short_notes": "* Combos from 1st hit",
    "startup": "i15",
    "tags": "",
    "target": "l,l,l",
    "video": ""
  },
  {
    "crush": "",
    "damage": "10101010",
    "gif": "",
    "id": "Jack-8-SIT.1,2,1,2",
    "image": "",
    "input": "SIT.1,2,1,2",
    "name": "Sit Punches",
    "notes": "* Combos from 1st hit\n* Alternate input SIT.2,1,2,1",
    "on_block": "-47",
    "on_ch": "",
    "on_hit": "-36",
    "recovery": "SIT",
    "short_notes": "* Combos from 1st hit\n* Alternate input SIT.2,1,2,1",
    "startup": "i15",
    "tags": "",
    "target": "l,l,l,l",
    "video": ""
  },
  {
    "crush": "",
    "damage": "21",
    "gif": "",
    "id": "Jack-8-SIT.1+2",
    "image": "",
    "input": "SIT.1+2",
    "name": "Ground Assault",
    "notes": "*",
    "on_block": "-44",
    "on_ch": "",
    "on_hit": "-12d",
    "recovery": "SIT",
    "short_notes": "*",
    "startup": "i24",
    "tags": "",
    "target": "m",
    "video": ""
  },
  {
    "crush": "js",
    "damage": "35",
    "gif": "",
    "id": "Jack-8-SIT.3+4",
    "image": "",
    "input": "SIT.3+4",
    "name": "Extra Pancake Press",
    "notes": "*\nLow crush",
    "on_block": "+13cg",
    "on_ch": "",
    "on_hit": "+20d",
    "recovery": "SIT",
    "short_notes": "*",
    "startup": "i54",
    "tags": "js",
    "target": "m",
    "video": ""
  },
  {
    "crush": "",
    "damage": "",
    "gif": "",
    "id": "Jack-8-SIT.b",
    "image": "",
    "input": "SIT.b",
    "name": "Backward Roll",
    "notes": "*",
    "on_block": "",
    "on_ch": "",
    "on_hit": "",
    "recovery": "",
    "short_notes": "*",
    "startup": "",
    "tags": "",
    "target": "",
    "video": ""
  },
  {
    "crush": "",
    "damage": "",
    "gif": "",
    "id": "Jack-8-SIT.f",
    "image": "",
    "input": "SIT.f",
    "name": "Forward Roll",
    "notes": "*",
    "on_block": "",
    "on_ch": "",
    "on_hit": "",
    "recovery": "",
    "short_notes": "*",
    "startup": "",
    "tags": "",
    "target": "",
    "video": ""
  },
  {
    "crush": "",
    "damage": "33",
    "gif": "",
    "id": "Jack-8-(During Enemy wall stun) 1+3",
    "image": "",
    "input": "(During Enemy wall stun) 1+3",
    "name": "Twin Drivers",
    "notes": "* Wall throw (Unbreakable)\n* Alternate input 2+4 or uf+1+2",
    "on_block": "!",
    "on_ch": "",
    "on_hit": "+0d",
    "recovery": "",
    "short_notes": "* Wall throw (Unbreakable)\n* Alternate input 2+4 or uf+1+2",
    "startup": "i12",
    "tags": "",
    "target": "t",
    "video": ""
  },
  {
    "crush": "",
    "damage": "35",
    "gif": "",
    "id": "Jack-8-1+3",
    "image": "",
    "input": "1+3",
    "name": "Rotary Catapult",
    "notes": "* Throw Break 1 or 2\n*",
    "on_block": "+0",
    "on_ch": "",
    "on_hit": "+1d",
    "recovery": "BT",
    "short_notes": "* Throw Break 1 or 2\n*",
    "startup": "i12",
    "tags": "",
    "target": "t",
    "video": ""
  },
  {
    "crush": "",
    "damage": "35",
    "gif": "",
    "id": "Jack-8-2+4",
    "image": "",
    "input": "2+4",
    "name": "Piston Gun Back Breaker",
    "notes": "* Throw Break 1 or 2\n* Side Switch",
    "on_block": "-6",
    "on_ch": "",
    "on_hit": "-3d",
    "recovery": "",
    "short_notes": "* Throw Break 1 or 2\n* Side Switch",
    "startup": "i12",
    "tags": "",
    "target": "t",
    "video": ""
  },
  {
    "crush": "",
    "damage": "70",
    "gif": "",
    "id": "Jack-8-Back Throw 1+3",
    "image": "",
    "input": "Back Throw 1+3",
    "name": "Spinal Crush",
    "notes": "* Unbreakable\n* Floor Break",
    "on_block": "!",
    "on_ch": "",
    "on_hit": "+3d",
    "recovery": "",
    "short_notes": "* Unbreakable",
    "startup": "i12",
    "tags": "fbr",
    "target": "t",
    "video": ""
  },
  {
    "crush": "",
    "damage": "70",
    "gif": "",
    "id": "Jack-8-Back Throw 2+4",
    "image": "",
    "input": "Back Throw 2+4",
    "name": "Throw Away",
    "notes": "* Unbreakable\n* Balcony Break",
    "on_block": "!",
    "on_ch": "",
    "on_hit": "+17d",
    "recovery": "",
    "short_notes": "* Unbreakable",
    "startup": "i12",
    "tags": "bbr",
    "target": "t",
    "video": ""
  },
  {
    "crush": "",
    "damage": "45 (57)",
    "gif": "",
    "id": "Jack-8-GMH.1+2",
    "image": "",
    "input": "GMH.1+2",
    "name": "Mimesis Overkill",
    "notes": "* 57 Damage if opponent hits the wall\n* Throw Break 1+2\n* Swaps positions on break",
    "on_block": "-6",
    "on_ch": "",
    "on_hit": "+0d",
    "recovery": "",
    "short_notes": "* 57 Damage if opponent hits the wall\n* Throw Break 1+2\n* Swaps positions on break",
    "startup": "i16",
    "tags": "",
    "target": "th",
    "video": ""
  },
  {
    "crush": "",
    "damage": "40",
    "gif": "",
    "id": "Jack-8-Left Throw",
    "image": "",
    "input": "Left Throw",
    "name": "Side Left Bomb",
    "notes": "* Throw Break 1\n* Balcony Break",
    "on_block": "-3",
    "on_ch": "",
    "on_hit": "+1d",
    "recovery": "",
    "short_notes": "* Throw Break 1",
    "startup": "i12",
    "tags": "bbr",
    "target": "t",
    "video": ""
  },
  {
    "crush": "",
    "damage": "40",
    "gif": "",
    "id": "Jack-8-Right Throw",
    "image": "",
    "input": "Right Throw",
    "name": "Father&#039;s Love",
    "notes": "* Throw Break 2\n* Side Swap",
    "on_block": "-3",
    "on_ch": "",
    "on_hit": "+0d",
    "recovery": "",
    "short_notes": "* Throw Break 2\n* Side Swap",
    "startup": "i12",
    "tags": "",
    "target": "t",
    "video": ""
  },
  {
    "crush": "",
    "damage": "50",
    "gif": "",
    "id": "Jack-8-db,n,f+1+2",
    "image": "",
    "input": "db,n,f+1+2",
    "name": "Pile Driver",
    "notes": "* Throw Break 1+2\n* Floor Break",
    "on_block": "-6",
    "on_ch": "",
    "on_hit": "-1d",
    "recovery": "",
    "short_notes": "* Throw Break 1+2",
    "startup": "i11",
    "tags": "fbr",
    "target": "t",
    "video": ""
  },
  {
    "crush": "",
    "damage": "25",
    "gif": "",
    "id": "Jack-8-db+2+3",
    "image": "",
    "input": "db+2+3",
    "name": "Body Smash",
    "notes": "* Throw Break 2\n* Floor Break",
    "on_block": "-2",
    "on_ch": "",
    "on_hit": "+14c",
    "recovery": "",
    "short_notes": "* Throw Break 2",
    "startup": "i11",
    "tags": "fbr",
    "target": "t",
    "video": ""
  },
  {
    "crush": "",
    "damage": "10",
    "gif": "",
    "id": "Jack-8-df,DF+2+4",
    "image": "",
    "input": "df,DF+2+4",
    "name": "Volcano Blaster",
    "notes": "* Throw Break 2\n*",
    "on_block": "-2",
    "on_ch": "",
    "on_hit": "+54a",
    "recovery": "",
    "short_notes": "* Throw Break 2\n*",
    "startup": "i11",
    "tags": "",
    "target": "t",
    "video": ""
  },
  {
    "crush": "",
    "damage": "10",
    "gif": "",
    "id": "Jack-8-df+2+4",
    "image": "",
    "input": "df+2+4",
    "name": "Volcano",
    "notes": "* Throw Break 2\n*",
    "on_block": "-2",
    "on_ch": "",
    "on_hit": "+26a",
    "recovery": "",
    "short_notes": "* Throw Break 2\n*",
    "startup": "i11",
    "tags": "",
    "target": "t",
    "video": ""
  },
  {
    "crush": "",
    "damage": "30",
    "gif": "",
    "id": "Jack-8-d+1+3",
    "image": "",
    "input": "d+1+3",
    "name": "Gun Bomb",
    "notes": "* Crouch Throw (Unbreakable)\n* Floor Break\n* Alternate input GMH.1+3",
    "on_block": "!",
    "on_ch": "",
    "on_hit": "+0d",
    "recovery": "",
    "short_notes": "* Crouch Throw (Unbreakable)\n* Alternate input GMH.1+3",
    "startup": "i12",
    "tags": "fbr",
    "target": "t",
    "video": ""
  },
  {
    "crush": "",
    "damage": "25",
    "gif": "",
    "id": "Jack-8-d+2+4",
    "image": "",
    "input": "d+2+4",
    "name": "Iron Gunman",
    "notes": "* Heat Engager\n\n* Cannot cancel into Heat Dash\n* Crouch Throw (Unbreakable)\n* Alternate input GMH.2+4",
    "on_block": "",
    "on_ch": "",
    "on_hit": "+6d",
    "recovery": "",
    "short_notes": "\n* Cannot cancel into Heat Dash\n* Crouch Throw (Unbreakable)\n* Alternate input GMH.2+4",
    "startup": "i12",
    "tags": "he",
    "target": "t",
    "video": ""
  },
  {
    "crush": "",
    "damage": "45",
    "gif": "",
    "id": "Jack-8-qcb+2",
    "image": "",
    "input": "qcb+2",
    "name": "Back Breaker",
    "notes": "* Throw Break 2",
    "on_block": "-2",
    "on_ch": "",
    "on_hit": "+12d",
    "recovery": "",
    "short_notes": "* Throw Break 2",
    "startup": "i11",
    "tags": "",
    "target": "t",
    "video": ""
  },
  {
    "crush": "",
    "damage": "40",
    "gif": "",
    "id": "Jack-8-qcf+1",
    "image": "",
    "input": "qcf+1",
    "name": "Pyramid Driver",
    "notes": "* Throw Break 1\n* Floor Break",
    "on_block": "-2",
    "on_ch": "",
    "on_hit": "-2d",
    "recovery": "",
    "short_notes": "* Throw Break 1",
    "startup": "i11",
    "tags": "fbr",
    "target": "t",
    "video": ""
  },
  {
    "crush": "",
    "damage": "35",
    "gif": "",
    "id": "Jack-8-uf+1+2",
    "image": "",
    "input": "uf+1+2",
    "name": "Ground Zero",
    "notes": "* Throw Break 1+2\n* Floor Break",
    "on_block": "-6",
    "on_ch": "",
    "on_hit": "-10d",
    "recovery": "",
    "short_notes": "* Throw Break 1+2",
    "startup": "i11",
    "tags": "fbr",
    "target": "t",
    "video": ""
  },
  {
    "crush": "",
    "damage": "40",
    "gif": "",
    "id": "Jack-8-uf+1+2,d,df+2",
    "image": "",
    "input": "uf+1+2,d,df+2",
    "name": "Lift Up Megaton hit",
    "notes": "* Throw Break 1+2\n* Balcony Break\n* Wallsplats opponent",
    "on_block": "-6",
    "on_ch": "",
    "on_hit": "+19a (-7)",
    "recovery": "",
    "short_notes": "* Throw Break 1+2\n* Wallsplats opponent",
    "startup": "i11",
    "tags": "bbr",
    "target": "t",
    "video": ""
  }
]
