[
  {
    "damage": "5",
    "gif": "",
    "id": "Lee-1",
    "input": "1",
    "name": "Jab",
    "notes": "",
    "on_block": "+1",
    "on_ch": "",
    "on_hit": "+8",
    "recovery": "",
    "startup": "i10",
    "target": "h"
  },
  {
    "damage": "5,9",
    "gif": "",
    "id": "Lee-1,2",
    "input": "1,2",
    "name": "",
    "notes": "Jail from 1st attack",
    "on_block": "-3",
    "on_ch": "",
    "on_hit": "+7",
    "recovery": "",
    "startup": "i12",
    "target": "h,h"
  },
  {
    "damage": "5,9,16",
    "gif": "",
    "id": "Lee-1,2,2",
    "input": "1,2,2",
    "name": "",
    "notes": "",
    "on_block": "-13",
    "on_ch": "",
    "on_hit": "-2",
    "recovery": "",
    "startup": "i20~21",
    "target": "h,h,m"
  },
  {
    "damage": "5,9,11",
    "gif": "",
    "id": "Lee-1,2,4",
    "input": "1,2,4",
    "name": "Left Right Mid Kick",
    "notes": "Goes into HMS by pressing 3. Crumples on ch.",
    "on_block": "-12",
    "on_ch": "+58",
    "on_hit": "-1",
    "recovery": "",
    "startup": "i18",
    "target": "h,h,m"
  },
  {
    "damage": "5,9,13",
    "gif": "",
    "id": "Lee-1,2:4",
    "input": "1,2&amp;#58;4",
    "name": "Left Right Mid Kick Cardinal",
    "notes": "Goes into HMS by pressing 3. Crumples on ch.",
    "on_block": "-12",
    "on_ch": "+58",
    "on_hit": "+5",
    "recovery": "",
    "startup": "i18",
    "target": "h,h,m"
  },
  {
    "damage": "5,6",
    "gif": "",
    "id": "Lee-1,3",
    "input": "1,3",
    "name": "",
    "notes": "",
    "on_block": "-11",
    "on_ch": "",
    "on_hit": "+0",
    "recovery": "",
    "startup": "i16",
    "target": "h,h"
  },
  {
    "damage": "5,6,4",
    "gif": "",
    "id": "Lee-1,3:3",
    "input": "1,3&amp;#58;3",
    "name": "",
    "notes": "",
    "on_block": "-11",
    "on_ch": "",
    "on_hit": "+0",
    "recovery": "",
    "startup": "i9",
    "target": "h,h,m"
  },
  {
    "damage": "5,6,4,15",
    "gif": "",
    "id": "Lee-1,3:3:3",
    "input": "1,3&amp;#58;3&amp;#58;3",
    "name": "Acid Rain Kick Combination",
    "notes": "Crumples.",
    "on_block": "-17",
    "on_ch": "",
    "on_hit": "+14",
    "recovery": "",
    "startup": "i21",
    "target": "h,h,m,h"
  },
  {
    "damage": "12",
    "gif": "",
    "id": "Lee-2+3",
    "input": "2+3",
    "name": "",
    "notes": "Heat Engager\n Powercrush. Cancelable with b,b.",
    "on_block": "+1",
    "on_ch": "",
    "on_hit": "+2",
    "recovery": "",
    "startup": "i16",
    "target": "m"
  },
  {
    "damage": "14",
    "gif": "",
    "id": "Lee-4",
    "input": "4",
    "name": "Machinegun kicks",
    "notes": "",
    "on_block": "-9",
    "on_ch": "",
    "on_hit": "+2",
    "recovery": "",
    "startup": "i11",
    "target": "h"
  },
  {
    "damage": "14,5",
    "gif": "",
    "id": "Lee-4,4",
    "input": "4,4",
    "name": "",
    "notes": "Launches on ch",
    "on_block": "-13",
    "on_ch": "",
    "on_hit": "-2",
    "recovery": "",
    "startup": "i10",
    "target": "h,h"
  },
  {
    "damage": "14,5,5",
    "gif": "",
    "id": "Lee-4,4,4",
    "input": "4,4,4",
    "name": "",
    "notes": "",
    "on_block": "-13",
    "on_ch": "",
    "on_hit": "-2",
    "recovery": "",
    "startup": "i10",
    "target": "h,h,h"
  },
  {
    "damage": "14,5,12",
    "gif": "",
    "id": "Lee-4,4:4",
    "input": "4,4&amp;#58;4",
    "name": "Machinegun Kicks Cardinal",
    "notes": "Heat Engager\n\n'''Heat Dash +5g +34d'''\n\n Does not engage heat on ch.",
    "on_block": "-9",
    "on_ch": "+29",
    "on_hit": "+17",
    "recovery": "",
    "startup": "i20",
    "target": "h,h,h"
  },
  {
    "damage": "23",
    "gif": "",
    "id": "Lee-b3+4",
    "input": "b3+4",
    "name": "",
    "notes": "Heat Engager\n\n'''Heat Dash +5g +34d'''\n\n Powercrush.",
    "on_block": "-7",
    "on_ch": "",
    "on_hit": "+17",
    "recovery": "",
    "startup": "i20",
    "target": "h"
  },
  {
    "damage": "14",
    "gif": "",
    "id": "Lee-df+4",
    "input": "df+4",
    "name": "",
    "notes": "",
    "on_block": "-9",
    "on_ch": "",
    "on_hit": "+5",
    "recovery": "",
    "startup": "i13-14",
    "target": "m"
  },
  {
    "damage": "14,22",
    "gif": "",
    "id": "Lee-df+4,4",
    "input": "df+4,4",
    "name": "Fabulous Whip",
    "notes": "Heat Engager\n\n'''Heat Dash +5g +34d'''\n\n df43 instead shifts into hms.",
    "on_block": "-9",
    "on_ch": "",
    "on_hit": "+10",
    "recovery": "",
    "startup": "i22-23",
    "target": "m,m"
  },
  {
    "damage": "26",
    "gif": "",
    "id": "Lee-ff3",
    "input": "ff3",
    "name": "",
    "notes": "Heat Engager\n\n'''Heat Dash +5g +36d'''\n\n Slight lowprofile",
    "on_block": "-9",
    "on_ch": "",
    "on_hit": "+17",
    "recovery": "",
    "startup": "i14~15",
    "target": "m"
  },
  {
    "damage": "37",
    "gif": "",
    "id": "Lee-H.2+3",
    "input": "H.2+3",
    "name": "",
    "notes": "",
    "on_block": "-15",
    "on_ch": "",
    "on_hit": "+0",
    "recovery": "",
    "startup": "i20",
    "target": "l"
  },
  {
    "damage": "26",
    "gif": "",
    "id": "Lee-hms.u3",
    "input": "hms.u3",
    "name": "",
    "notes": "Heat Engager\n\n'''Heat Dash +5g +36d'''\n",
    "on_block": "-9",
    "on_ch": "",
    "on_hit": "+17",
    "recovery": "",
    "startup": "i20~22",
    "target": "m"
  }
]
