[
    {
        "crush": "pc",
        "damage": "12 (12)",
        "gif": "",
        "id": "Leo-2+3",
        "image": "",
        "input": "2+3",
        "name": "Heat Burst",
        "notes": "* Heat Burst\nPower crush",
        "on_block": "+1~+2",
        "on_ch": "",
        "on_hit": "+2c",
        "recovery": "",
        "short_notes": "",
        "startup": "i16~17",
        "tags": "hb pc",
        "target": "m",
        "video": ""
    },
    {
        "crush": "",
        "damage": "8,13,14 (35)",
        "gif": "",
        "id": "Leo-H.KNK.2+3",
        "image": "",
        "input": "H.KNK.2+3",
        "name": "Ultimate Huo Jian Qiang Fist",
        "notes": "* Heat Smash\n* Balcony Break",
        "on_block": "-13~-12",
        "on_ch": "",
        "on_hit": "+31a (+13)",
        "recovery": "",
        "short_notes": "",
        "startup": "i20~21",
        "tags": "hs bbr",
        "target": "l,m,m",
        "video": ""
    },
    {
        "crush": "",
        "damage": "14,13,23 (50)",
        "gif": "",
        "id": "Leo-H.2+3",
        "image": "",
        "input": "H.2+3",
        "name": "Ultimate Feng Huo Lun Kick",
        "notes": "* Heat Smash\n* Balcony Break\n* Enter CD +16g with df on block",
        "on_block": "+8~+9",
        "on_ch": "",
        "on_hit": "+5a",
        "recovery": "",
        "short_notes": "* Enter CD +16g with df on block",
        "startup": "i16~17",
        "tags": "hs bbr",
        "target": "m,m,h",
        "video": ""
    },
    {
        "crush": "pc",
        "damage": "55+",
        "gif": "",
        "id": "Leo-R.df+1+2",
        "image": "",
        "input": "R.df+1+2",
        "name": "Transcendent Blow",
        "notes": "* Rage Art\n* Removes Recoverable Health\nPower crush",
        "on_block": "-15",
        "on_ch": "",
        "on_hit": "+0d",
        "recovery": "",
        "short_notes": "* Rage Art\n* Removes Recoverable Health",
        "startup": "i20",
        "tags": "pc",
        "target": "m",
        "video": ""
    },
    {
        "crush": "",
        "damage": "5",
        "gif": "",
        "id": "Leo-1",
        "image": "",
        "input": "1",
        "name": "Jab",
        "notes": "",
        "on_block": "+1",
        "on_ch": "",
        "on_hit": "+8",
        "recovery": "",
        "short_notes": "",
        "startup": "i10",
        "tags": "",
        "target": "h",
        "video": ""
    },
    {
        "crush": "",
        "damage": "5, 10",
        "gif": "",
        "id": "Leo-1,2",
        "image": "",
        "input": "1,2",
        "name": "He Zi Shou",
        "notes": "* Jail from 1st attack\n* Enter KNK -9 +2 with b",
        "on_block": "-3",
        "on_ch": "",
        "on_hit": "+8",
        "recovery": "",
        "short_notes": "* Jail from 1st attack\n* Enter KNK -9 +2 with b",
        "startup": "i12",
        "tags": "",
        "target": "h, h",
        "video": ""
    },
    {
        "crush": "",
        "damage": "5, 10, 16",
        "gif": "",
        "id": "Leo-1,2,1",
        "image": "",
        "input": "1,2,1",
        "name": "",
        "notes": "Combo from 2nd CH",
        "on_block": "-5~-4",
        "on_ch": "+9",
        "on_hit": "+6",
        "recovery": "",
        "short_notes": "Combo from 2nd CH",
        "startup": "i20~21",
        "tags": "",
        "target": "h, h, h",
        "video": ""
    },
    {
        "crush": "",
        "damage": "5, 10, 16, 21",
        "gif": "",
        "id": "Leo-1,2,1,1",
        "image": "",
        "input": "1,2,1,1",
        "name": "Liang Yi Zhou",
        "notes": "*\nBalcony Break\n* Combo from 3rd Hit",
        "on_block": "-13",
        "on_ch": "",
        "on_hit": "+12a (+3)",
        "recovery": "",
        "short_notes": "*\n* Combo from 3rd Hit",
        "startup": "i18",
        "tags": "bbr",
        "target": "h, h, h, m",
        "video": ""
    },
    {
        "crush": "",
        "damage": "5, 10, 16, 30",
        "gif": "",
        "id": "Leo-1,2,1,4",
        "image": "",
        "input": "1,2,1,4",
        "name": "Wai Bai Tui",
        "notes": "*\nBalcony Break\n* Combo from 3rd Hit",
        "on_block": "-6~-4",
        "on_ch": "",
        "on_hit": "+32a (+6)",
        "recovery": "",
        "short_notes": "*\n* Combo from 3rd Hit",
        "startup": "i21~23",
        "tags": "bbr",
        "target": "h, h, h, h",
        "video": ""
    },
    {
        "crush": "",
        "damage": "5, 10, 15",
        "gif": "",
        "id": "Leo-1,2,4",
        "image": "",
        "input": "1,2,4",
        "name": "Ye Chui",
        "notes": "Combo from 2nd CH",
        "on_block": "-13",
        "on_ch": "+8d",
        "on_hit": "+3",
        "recovery": "",
        "short_notes": "Combo from 2nd CH",
        "startup": "i24",
        "tags": "",
        "target": "h, h, L",
        "video": ""
    },
    {
        "crush": "",
        "damage": "5, 17",
        "gif": "",
        "id": "Leo-1,4",
        "image": "",
        "input": "1,4",
        "name": "Lan Tan Jin Ji Du Li",
        "notes": "* Jail from 1st attack",
        "on_block": "-5",
        "on_ch": "",
        "on_hit": "+11",
        "recovery": "KNK",
        "short_notes": "* Jail from 1st attack",
        "startup": "i16",
        "tags": "",
        "target": "h, h",
        "video": ""
    },
    {
        "crush": "",
        "damage": "9",
        "gif": "",
        "id": "Leo-2",
        "image": "",
        "input": "2",
        "name": "Right Jab",
        "notes": "",
        "on_block": "-1",
        "on_ch": "",
        "on_hit": "+5",
        "recovery": "",
        "short_notes": "",
        "startup": "i11",
        "tags": "",
        "target": "h",
        "video": ""
    },
    {
        "crush": "",
        "damage": "9, 12",
        "gif": "",
        "id": "Leo-2,1",
        "image": "",
        "input": "2,1",
        "name": "Xiang Long Shi Chong Tian Zhang",
        "notes": "Jail from 1st attack",
        "on_block": "-7~-6",
        "on_ch": "",
        "on_hit": "+4",
        "recovery": "",
        "short_notes": "Jail from 1st attack",
        "startup": "i16~17",
        "tags": "",
        "target": "h, h",
        "video": ""
    },
    {
        "crush": "",
        "damage": "9, 20",
        "gif": "",
        "id": "Leo-2,2",
        "image": "",
        "input": "2,2",
        "name": "Xiang Long Shi Ling Zhou",
        "notes": "Combo from 1st Hit",
        "on_block": "-12",
        "on_ch": "",
        "on_hit": "+6",
        "recovery": "",
        "short_notes": "Combo from 1st Hit",
        "startup": "i22",
        "tags": "",
        "target": "h, m",
        "video": ""
    },
    {
        "crush": "",
        "damage": "15",
        "gif": "",
        "id": "Leo-3",
        "image": "",
        "input": "3",
        "name": "",
        "notes": "",
        "on_block": "-8",
        "on_ch": "",
        "on_hit": "+4",
        "recovery": "",
        "short_notes": "",
        "startup": "i14",
        "tags": "",
        "target": "h",
        "video": ""
    },
    {
        "crush": "",
        "damage": "15, 10",
        "gif": "",
        "id": "Leo-3,2",
        "image": "",
        "input": "3,2",
        "name": "",
        "notes": "* Combo from 1st hit\n* Enter BOK -6 +5 with d",
        "on_block": "-2",
        "on_ch": "",
        "on_hit": "+9",
        "recovery": "",
        "short_notes": "* Combo from 1st hit\n* Enter BOK -6 +5 with d",
        "startup": "i19",
        "tags": "",
        "target": "h, h",
        "video": ""
    },
    {
        "crush": "",
        "damage": "15, 10, 26",
        "gif": "",
        "id": "Leo-3,2,3",
        "image": "",
        "input": "3,2,3",
        "name": "Wu Dang Xuan Feng Jiao",
        "notes": "*\nTornado\n*\nBalcony Break\n* Combo from 2nd CH\n* Cancel to -15 -4 with B",
        "on_block": "-7~-6",
        "on_ch": "",
        "on_hit": "+13a (+4)",
        "recovery": "",
        "short_notes": "*\n*\n* Combo from 2nd CH\n* Cancel to -15 -4 with B",
        "startup": "i23~24",
        "tags": "trn bbr",
        "target": "h, h, m",
        "video": ""
    },
    {
        "crush": "",
        "damage": "15, 10, 14",
        "gif": "",
        "id": "Leo-3,2,4",
        "image": "",
        "input": "3,2,4",
        "name": "Wu Dang Jin Ji Du Li",
        "notes": "* Combo from 2nd CH",
        "on_block": "+9~+10",
        "on_ch": "+19",
        "on_hit": "+15g",
        "recovery": "KNK",
        "short_notes": "* Combo from 2nd CH",
        "startup": "i22~23",
        "tags": "",
        "target": "h, h, m",
        "video": ""
    },
    {
        "crush": "",
        "damage": "17",
        "gif": "",
        "id": "Leo-4",
        "image": "",
        "input": "4",
        "name": "",
        "notes": "",
        "on_block": "-7",
        "on_ch": "+31a",
        "on_hit": "+6",
        "recovery": "",
        "short_notes": "",
        "startup": "i12",
        "tags": "",
        "target": "h",
        "video": ""
    },
    {
        "crush": "pc7~",
        "damage": "25",
        "gif": "",
        "id": "Leo-1+2",
        "image": "",
        "input": "1+2",
        "name": "Dual Thunder Fists",
        "notes": "* Balcony Break\n* Chip damage on block\nPower crush 7~",
        "on_block": "-12",
        "on_ch": "",
        "on_hit": "+11a (+2)",
        "recovery": "",
        "short_notes": "",
        "startup": "i25",
        "tags": "bbr chp pc7~",
        "target": "m",
        "video": ""
    },
    {
        "crush": "",
        "damage": "14",
        "gif": "",
        "id": "Leo-f+2",
        "image": "",
        "input": "f+2",
        "name": "",
        "notes": "",
        "on_block": "0~+2",
        "on_ch": "",
        "on_hit": "+6",
        "recovery": "",
        "short_notes": "",
        "startup": "i14~16",
        "tags": "",
        "target": "h",
        "video": ""
    },
    {
        "crush": "",
        "damage": "14, 21",
        "gif": "",
        "id": "Leo-f+2,2",
        "image": "",
        "input": "f+2,2",
        "name": "Heng Da Er Lang Dan Shan",
        "notes": "Combo from 1st hit",
        "on_block": "-12~-11",
        "on_ch": "+25d",
        "on_hit": "+8",
        "recovery": "",
        "short_notes": "Combo from 1st hit",
        "startup": "i23~24",
        "tags": "",
        "target": "h, m",
        "video": ""
    },
    {
        "crush": "",
        "damage": "14, 16",
        "gif": "",
        "id": "Leo-f+2,4",
        "image": "",
        "input": "f+2,4",
        "name": "Heng Da Bai Tui",
        "notes": "* Jail from 1st attack\n* Enter CD -1 +7 with df",
        "on_block": "-1~0",
        "on_ch": "",
        "on_hit": "+7",
        "recovery": "",
        "short_notes": "* Jail from 1st attack\n* Enter CD -1 +7 with df",
        "startup": "i22~23",
        "tags": "",
        "target": "h, h",
        "video": ""
    },
    {
        "crush": "js16~",
        "damage": "14, 16, 20",
        "gif": "",
        "id": "Leo-f+2,4,LTG.3",
        "image": "",
        "input": "f+2,4,LTG.3",
        "name": "Jue Zhao Heng Da Bai Tui",
        "notes": "* Balcony Break\n* Spike\n* Chip damage on block\n* Combo from 1st hit\n* Enter BOK +4c [[Leo combos#Mini-combos|+19d]] with d\nLow crush 16~",
        "on_block": "+1c~+4c",
        "on_ch": "",
        "on_hit": "+16d",
        "recovery": "",
        "short_notes": "* Combo from 1st hit\n* Enter BOK +4c [[Leo combos#Mini-combos|+19d]] with d",
        "startup": ",i32~35",
        "tags": "bbr spk chp js16~",
        "target": "h, h, M",
        "video": ""
    },
    {
        "crush": "",
        "damage": "23",
        "gif": "",
        "id": "Leo-f+3",
        "image": "",
        "input": "f+3",
        "name": "Bai Tui",
        "notes": "* Enter BOK +2 +6 [[Leo combos#Mini-combos|+29a]] with d",
        "on_block": "0~+1",
        "on_ch": "+27a",
        "on_hit": "+4",
        "recovery": "",
        "short_notes": "* Enter BOK +2 +6 [[Leo combos#Mini-combos|+29a]] with d",
        "startup": "i20~21",
        "tags": "",
        "target": "h",
        "video": ""
    },
    {
        "crush": "",
        "damage": "14",
        "gif": "",
        "id": "Leo-f+4",
        "image": "",
        "input": "f+4",
        "name": "Jin Ji Du Li",
        "notes": "* Enter CD -5 +1 +5 with df",
        "on_block": "+9~+10",
        "on_ch": "+19",
        "on_hit": "+15g",
        "recovery": "KNK",
        "short_notes": "* Enter CD -5 +1 +5 with df",
        "startup": "i17~18",
        "tags": "",
        "target": "m",
        "video": ""
    },
    {
        "crush": "",
        "damage": "24",
        "gif": "",
        "id": "Leo-f+1+2",
        "image": "",
        "input": "f+1+2",
        "name": "Bei Zhe Kao",
        "notes": "* Balcony Break",
        "on_block": "-14~-13",
        "on_ch": "+56a",
        "on_hit": "+10a (+1)",
        "recovery": "",
        "short_notes": "",
        "startup": "i17~18",
        "tags": "bbr",
        "target": "m",
        "video": ""
    },
    {
        "crush": "",
        "damage": "21",
        "gif": "",
        "id": "Leo-f+2+3",
        "image": "",
        "input": "f+2+3",
        "name": "Xiang Chui",
        "notes": "* Balcony Break",
        "on_block": "-9~-8",
        "on_ch": "",
        "on_hit": "+11a (+2)",
        "recovery": "",
        "short_notes": "",
        "startup": "i20~21",
        "tags": "bbr",
        "target": "h",
        "video": ""
    },
    {
        "crush": "",
        "damage": "24",
        "gif": "",
        "id": "Leo-f+3+4",
        "image": "",
        "input": "f+3+4",
        "name": "Yellow Crane",
        "notes": "* Tornado\n* Balcony Break\n* Chip damage on block",
        "on_block": "0~-1",
        "on_ch": "+71a (+55)",
        "on_hit": "+8",
        "recovery": "",
        "short_notes": "",
        "startup": "i17~18",
        "tags": "trn bbr chp",
        "target": "h",
        "video": ""
    },
    {
        "crush": "",
        "damage": "13",
        "gif": "",
        "id": "Leo-df+1",
        "image": "",
        "input": "df+1",
        "name": "Quick Upper",
        "notes": "",
        "on_block": "-1~0",
        "on_ch": "",
        "on_hit": "+7",
        "recovery": "",
        "short_notes": "",
        "startup": "i13~14",
        "tags": "",
        "target": "m",
        "video": ""
    },
    {
        "crush": "",
        "damage": "13, 20",
        "gif": "",
        "id": "Leo-df+1,2",
        "image": "",
        "input": "df+1,2",
        "name": "Shuang Huan Da",
        "notes": "*\nTornado\n*\nBalcony Break\n* Combo from 1st CH with 7?F delay\n* Move can be delayed 8?F",
        "on_block": "-6",
        "on_ch": "+34d (+26)",
        "on_hit": "+9d",
        "recovery": "",
        "short_notes": "*\n*\n* Combo from 1st CH with 7?F delay\n* Move can be delayed 8?F",
        "startup": "i18",
        "tags": "trn bbr",
        "target": "m, h",
        "video": ""
    },
    {
        "crush": "",
        "damage": "15",
        "gif": "",
        "id": "Leo-df+2",
        "image": "",
        "input": "df+2",
        "name": "Sheng Pao",
        "notes": "",
        "on_block": "-13~-12",
        "on_ch": "",
        "on_hit": "+28a (+18)",
        "recovery": "",
        "short_notes": "",
        "startup": "i15~16",
        "tags": "",
        "target": "m",
        "video": ""
    },
    {
        "crush": "",
        "damage": "22",
        "gif": "",
        "id": "Leo-df+3",
        "image": "",
        "input": "df+3",
        "name": "Chuan Pao",
        "notes": "* Homing\n* Balcony Break",
        "on_block": "-9~-7",
        "on_ch": "+27a (-9)",
        "on_hit": "+6a (-3)",
        "recovery": "",
        "short_notes": "",
        "startup": "i17~19",
        "tags": "hom bbr",
        "target": "m",
        "video": ""
    },
    {
        "crush": "",
        "damage": "14",
        "gif": "",
        "id": "Leo-df+4",
        "image": "",
        "input": "df+4",
        "name": "",
        "notes": "",
        "on_block": "-6",
        "on_ch": "",
        "on_hit": "+5",
        "recovery": "",
        "short_notes": "",
        "startup": "i13",
        "tags": "",
        "target": "m",
        "video": ""
    },
    {
        "crush": "cs6~",
        "damage": "20",
        "gif": "",
        "id": "Leo-df+2+3",
        "image": "",
        "input": "df+2+3",
        "name": "Gui Xi",
        "notes": "High crush 6~",
        "on_block": "-12~-11",
        "on_ch": "+21d",
        "on_hit": "+5",
        "recovery": "",
        "short_notes": "",
        "startup": "i21~22",
        "tags": "cs6~",
        "target": "L",
        "video": ""
    },
    {
        "crush": "",
        "damage": "18",
        "gif": "",
        "id": "Leo-d+1",
        "image": "",
        "input": "d+1",
        "name": "Fu Hu",
        "notes": "* Spike\n* Enter FC with d",
        "on_block": "-2~-1",
        "on_ch": "+13",
        "on_hit": "+5",
        "recovery": "",
        "short_notes": "* Enter FC with d",
        "startup": "i18~19",
        "tags": "spk",
        "target": "m",
        "video": ""
    },
    {
        "crush": "",
        "damage": "23",
        "gif": "",
        "id": "Leo-d+2",
        "image": "",
        "input": "d+2",
        "name": "Pi Zhong",
        "notes": "* Spike",
        "on_block": "+4c",
        "on_ch": "+56a",
        "on_hit": "+9c",
        "recovery": "",
        "short_notes": "",
        "startup": "i21",
        "tags": "spk",
        "target": "m",
        "video": ""
    },
    {
        "crush": "cs4~",
        "damage": "10",
        "gif": "",
        "id": "Leo-d+3",
        "image": "",
        "input": "d+3",
        "name": "Crouch Spin Kick",
        "notes": "High crush 4~",
        "on_block": "-17",
        "on_ch": "",
        "on_hit": "-6",
        "recovery": "",
        "short_notes": "",
        "startup": "i16",
        "tags": "cs4~",
        "target": "l",
        "video": ""
    },
    {
        "crush": "",
        "damage": "13",
        "gif": "",
        "id": "Leo-d+4",
        "image": "",
        "input": "d+4",
        "name": "Sao Tang Ti",
        "notes": "",
        "on_block": "-11~-10",
        "on_ch": "",
        "on_hit": "+0",
        "recovery": "",
        "short_notes": "",
        "startup": "i16~17",
        "tags": "",
        "target": "L",
        "video": ""
    },
    {
        "crush": "",
        "damage": "13, 23",
        "gif": "",
        "id": "Leo-d+4,2",
        "image": "",
        "input": "d+4,2",
        "name": "Shang Bu Zhuang Zhang",
        "notes": "* Combo from 1st CH\n* Gain LTG -11d -1d on hit with 1+2",
        "on_block": "-5~-4",
        "on_ch": "+3d",
        "on_hit": "-7d",
        "recovery": "",
        "short_notes": "* Combo from 1st CH\n* Gain LTG -11d -1d on hit with 1+2",
        "startup": "i26~27",
        "tags": "",
        "target": "L, h",
        "video": ""
    },
    {
        "crush": "cs6~",
        "damage": "",
        "gif": "",
        "id": "Leo-d+1+2",
        "image": "",
        "input": "d+1+2",
        "name": "Fo Bu",
        "notes": "High crush 6~",
        "on_block": "",
        "on_ch": "",
        "on_hit": "",
        "recovery": "BOK",
        "short_notes": "",
        "startup": "",
        "tags": "cs6~",
        "target": "",
        "video": ""
    },
    {
        "crush": "cs4~",
        "damage": "7",
        "gif": "",
        "id": "Leo-d+3+4",
        "image": "",
        "input": "d+3+4",
        "name": "Crouch Shin Kick",
        "notes": "High crush 4~",
        "on_block": "-15",
        "on_ch": "",
        "on_hit": "-4",
        "recovery": "",
        "short_notes": "",
        "startup": "i12",
        "tags": "cs4~",
        "target": "l",
        "video": ""
    },
    {
        "crush": "cs4~",
        "damage": "6",
        "gif": "",
        "id": "Leo-db+1",
        "image": "",
        "input": "db+1",
        "name": "Crouch Jab",
        "notes": "High crush 4~",
        "on_block": "-5",
        "on_ch": "",
        "on_hit": "+6",
        "recovery": "",
        "short_notes": "",
        "startup": "i10",
        "tags": "cs4~",
        "target": "s",
        "video": ""
    },
    {
        "crush": "",
        "damage": "16",
        "gif": "",
        "id": "Leo-db+2",
        "image": "",
        "input": "db+2",
        "name": "",
        "notes": "",
        "on_block": "-9~-8",
        "on_ch": "",
        "on_hit": "+5",
        "recovery": "",
        "short_notes": "",
        "startup": "i16~17",
        "tags": "",
        "target": "m",
        "video": ""
    },
    {
        "crush": "js12~",
        "damage": "16, 24",
        "gif": "",
        "id": "Leo-db+2,4",
        "image": "",
        "input": "db+2,4",
        "name": "Bei Zhan Juan Long Jiao",
        "notes": "* Heat Engager\n\n* Heat Dash +5g, [[Leo combos#Staples|+64a (+42)]]\n\n* Balcony Break\n* Combo from 1st hit\nLow crush 12~",
        "on_block": "-9~-7",
        "on_ch": "",
        "on_hit": "+12a (+3)",
        "recovery": "",
        "short_notes": "\n* Heat Dash +5g, [[Leo combos#Staples|+64a (+42)]]\n\n* Combo from 1st hit",
        "startup": "i24~26",
        "tags": "he bbr js12~",
        "target": "m, h",
        "video": ""
    },
    {
        "crush": "",
        "damage": "23",
        "gif": "",
        "id": "Leo-db+3",
        "image": "",
        "input": "db+3",
        "name": "Lie Huo Fan Jiao",
        "notes": "No crouching state",
        "on_block": "-8~-9",
        "on_ch": "",
        "on_hit": "+38a (+28)",
        "recovery": "",
        "short_notes": "No crouching state",
        "startup": "i31~32",
        "tags": "",
        "target": "h",
        "video": ""
    },
    {
        "crush": "cs11~",
        "damage": "11",
        "gif": "",
        "id": "Leo-db+4",
        "image": "",
        "input": "db+4",
        "name": "",
        "notes": "* Clean hit +2\n* Staggers on block\n* Causes float on hit if db+4,1 is input\nHigh crush 11~",
        "on_block": "-31~-29",
        "on_ch": "+33a",
        "on_hit": "+2",
        "recovery": "",
        "short_notes": "* Clean hit +2\n* Staggers on block\n* Causes float on hit if db+4,1 is input",
        "startup": "i20~22",
        "tags": "cs11~",
        "target": "L",
        "video": ""
    },
    {
        "crush": "",
        "damage": "11, 27",
        "gif": "",
        "id": "Leo-db+4,1",
        "image": "",
        "input": "db+4,1",
        "name": "Qian Sao Lei Wang Quan",
        "notes": "* Balcony Break\n* Combo from 1st hit\n** +14a (+7)",
        "on_block": "-16~-15",
        "on_ch": "",
        "on_hit": "+8a",
        "recovery": "",
        "short_notes": "* Combo from 1st hit\n** +14a (+7)",
        "startup": "i25~26",
        "tags": "bbr",
        "target": "L, m",
        "video": ""
    },
    {
        "crush": "",
        "damage": "11, 27, 20",
        "gif": "",
        "id": "Leo-db+4,1,LTG.1+2",
        "image": "",
        "input": "db+4,1,LTG.1+2",
        "name": "Jue Zhao Qian Sao Lei Wang Quan",
        "notes": "* Balcony Break\n* Chip damage on block\n* Combo from 1st hit\n** +27a (+17)",
        "on_block": "-15~-14",
        "on_ch": "",
        "on_hit": "+6a (-3)",
        "recovery": "",
        "short_notes": "* Combo from 1st hit\n** +27a (+17)",
        "startup": ",i15~16",
        "tags": "bbr chp",
        "target": "L, m, m",
        "video": ""
    },
    {
        "crush": "",
        "damage": "17",
        "gif": "",
        "id": "Leo-db+1+2",
        "image": "",
        "input": "db+1+2",
        "name": "",
        "notes": "* Enter BOK -12 +4 with d",
        "on_block": "-9~-7",
        "on_ch": "",
        "on_hit": "+7",
        "recovery": "",
        "short_notes": "* Enter BOK -12 +4 with d",
        "startup": "i21~23",
        "tags": "",
        "target": "m",
        "video": ""
    },
    {
        "crush": "",
        "damage": "17, 20",
        "gif": "",
        "id": "Leo-db+1+2,1",
        "image": "",
        "input": "db+1+2,1",
        "name": "Ba Wang Zhe Jiang",
        "notes": "* Balcony Break\n* Combo from 1st hit with delay",
        "on_block": "-12~-11",
        "on_ch": "",
        "on_hit": "+22a (+17)",
        "recovery": "",
        "short_notes": "* Combo from 1st hit with delay",
        "startup": "i17~18",
        "tags": "bbr",
        "target": "m, m",
        "video": ""
    },
    {
        "crush": "",
        "damage": "17",
        "gif": "",
        "id": "Leo-b+1",
        "image": "",
        "input": "b+1",
        "name": "",
        "notes": "",
        "on_block": "-12~-11",
        "on_ch": "",
        "on_hit": "+1",
        "recovery": "",
        "short_notes": "",
        "startup": "i18~19",
        "tags": "",
        "target": "m",
        "video": ""
    },
    {
        "crush": "",
        "damage": "17, 14",
        "gif": "",
        "id": "Leo-b+1,4",
        "image": "",
        "input": "b+1,4",
        "name": "Ding Zhou Jin Ji Du Li",
        "notes": "* Combo from 1st CH",
        "on_block": "+9",
        "on_ch": "+19",
        "on_hit": "+15g",
        "recovery": "KNK",
        "short_notes": "* Combo from 1st CH",
        "startup": "i23",
        "tags": "",
        "target": "m, m",
        "video": ""
    },
    {
        "crush": "",
        "damage": "17, 18",
        "gif": "",
        "id": "Leo-b+1,1+2",
        "image": "",
        "input": "b+1,1+2",
        "name": "Ding Zhou Meng Po Kao",
        "notes": "* Combo from 1st hit\n* Enter BOK -10 +11 with d",
        "on_block": "-12~-11",
        "on_ch": "",
        "on_hit": "+9",
        "recovery": "",
        "short_notes": "* Combo from 1st hit\n* Enter BOK -10 +11 with d",
        "startup": "i22~23",
        "tags": "",
        "target": "m, m",
        "video": ""
    },
    {
        "crush": "ps5~12",
        "damage": "",
        "gif": "",
        "id": "Leo-b+1+3",
        "image": "",
        "input": "b+1+3",
        "name": "Shi Zi Xiao Zhang Kou",
        "notes": "* Parries high and mid punches and kicks\nParry state 5~12",
        "on_block": "",
        "on_ch": "",
        "on_hit": "",
        "recovery": "",
        "short_notes": "* Parries high and mid punches and kicks",
        "startup": "",
        "tags": "ps5~12",
        "target": "",
        "video": ""
    },
    {
        "crush": "",
        "damage": "30",
        "gif": "",
        "id": "Leo-b+1+3,P.2",
        "image": "",
        "input": "b+1+3,P.2",
        "name": "Shang Bu Zhuang Quan",
        "notes": "* Balcony Break\n* Combo from parry\n* Gain LTG on hit",
        "on_block": "-9~-8",
        "on_ch": "",
        "on_hit": "-9a",
        "recovery": "",
        "short_notes": "* Combo from parry\n* Gain LTG on hit",
        "startup": "i14~15",
        "tags": "bbr",
        "target": "m",
        "video": ""
    },
    {
        "crush": "",
        "damage": "11",
        "gif": "",
        "id": "Leo-b+2",
        "image": "",
        "input": "b+2",
        "name": "",
        "notes": "",
        "on_block": "-11",
        "on_ch": "",
        "on_hit": "+0",
        "recovery": "",
        "short_notes": "",
        "startup": "i14",
        "tags": "",
        "target": "m",
        "video": ""
    },
    {
        "crush": "",
        "damage": "11, 11",
        "gif": "",
        "id": "Leo-b+2,1",
        "image": "",
        "input": "b+2,1",
        "name": "Wu Hu Chu Dong",
        "notes": "Combo from 1st hit",
        "on_block": "-4~-3",
        "on_ch": "",
        "on_hit": "+7",
        "recovery": "",
        "short_notes": "Combo from 1st hit",
        "startup": "i22~23",
        "tags": "",
        "target": "m, h",
        "video": ""
    },
    {
        "crush": "",
        "damage": "11, 21",
        "gif": "",
        "id": "Leo-b+2,1+2",
        "image": "",
        "input": "b+2,1+2",
        "name": "Er Lang Dan Shan",
        "notes": "* Heat Engager\n\n* Heat Dash +5 [[Leo combos#Staples|+67a (+50)]]\n\n* Combo from 1st hit",
        "on_block": "-11~-10",
        "on_ch": "",
        "on_hit": "+8",
        "recovery": "",
        "short_notes": "\n* Heat Dash +5 [[Leo combos#Staples|+67a (+50)]]\n\n* Combo from 1st hit",
        "startup": "i27~28",
        "tags": "he",
        "target": "m, m",
        "video": ""
    },
    {
        "crush": "ps5~12",
        "damage": "",
        "gif": "",
        "id": "Leo-b+2+4",
        "image": "",
        "input": "b+2+4",
        "name": "Shi Zi Zhou",
        "notes": "* Balcony Break\n* Parries high and mid punches and kicks\n* Side switch on punch parry (+5)\n* 25 damage on kick parry (+1d), does not Balcony Break\nParry state 5~12",
        "on_block": "",
        "on_ch": "",
        "on_hit": "",
        "recovery": "",
        "short_notes": "* Parries high and mid punches and kicks\n* Side switch on punch parry (+5)\n* 25 damage on kick parry (+1d), does not Balcony Break",
        "startup": "",
        "tags": "bbr ps5~12",
        "target": "",
        "video": ""
    },
    {
        "crush": "",
        "damage": "12",
        "gif": "",
        "id": "Leo-b+3",
        "image": "",
        "input": "b+3",
        "name": "",
        "notes": "",
        "on_block": "-7~-6",
        "on_ch": "",
        "on_hit": "+4",
        "recovery": "",
        "short_notes": "",
        "startup": "i14~15",
        "tags": "",
        "target": "m",
        "video": ""
    },
    {
        "crush": "",
        "damage": "12, 13",
        "gif": "",
        "id": "Leo-b+3,1",
        "image": "",
        "input": "b+3,1",
        "name": "Ying Mian Tui",
        "notes": "* Spike\n* Combo from 1st hit\n* Enter BOK -8 +5 with d\n* Enter KNK -10 +1 with b",
        "on_block": "-10",
        "on_ch": "",
        "on_hit": "+4",
        "recovery": "",
        "short_notes": "* Combo from 1st hit\n* Enter BOK -8 +5 with d\n* Enter KNK -10 +1 with b",
        "startup": "i20",
        "tags": "spk",
        "target": "m, m",
        "video": ""
    },
    {
        "crush": "",
        "damage": "12, 13, 25",
        "gif": "",
        "id": "Leo-b+3,1,LTG.2",
        "image": "",
        "input": "b+3,1,LTG.2",
        "name": "Jue Zhao Ying Mian Tui",
        "notes": "* Balcony Break\n* Chip damage on block\n* Combo from 1st hit",
        "on_block": "-13",
        "on_ch": "",
        "on_hit": "+10a",
        "recovery": "",
        "short_notes": "* Combo from 1st hit",
        "startup": ",i17",
        "tags": "bbr chp",
        "target": "m, m, m",
        "video": ""
    },
    {
        "crush": "",
        "damage": "13",
        "gif": "",
        "id": "Leo-b+4",
        "image": "",
        "input": "b+4",
        "name": "",
        "notes": "",
        "on_block": "-8",
        "on_ch": "",
        "on_hit": "+5",
        "recovery": "",
        "short_notes": "",
        "startup": "i18",
        "tags": "",
        "target": "m",
        "video": ""
    },
    {
        "crush": "",
        "damage": "13, 20",
        "gif": "",
        "id": "Leo-b+4,1",
        "image": "",
        "input": "b+4,1",
        "name": "Dragon's Impact",
        "notes": "** Balcony Break\n* Combo from 1st hit\n* Cancel to FC -16 -3 with D",
        "on_block": "-12~-11",
        "on_ch": "",
        "on_hit": "+15a (+6)",
        "recovery": "",
        "short_notes": "* Combo from 1st hit\n* Cancel to FC -16 -3 with D",
        "startup": "i30~31",
        "tags": "bbr",
        "target": "m, m",
        "video": ""
    },
    {
        "crush": "",
        "damage": "13, 14",
        "gif": "",
        "id": "Leo-b+4,1~4",
        "image": "",
        "input": "b+4,1~4",
        "name": "Dragon's Impact > Jin Ji Du Li",
        "notes": "* Combo from 1st hit\n* Enter CD -5 +1 +5 with df",
        "on_block": "+9~+10",
        "on_ch": "+19",
        "on_hit": "+15g",
        "recovery": "KNK",
        "short_notes": "* Combo from 1st hit\n* Enter CD -5 +1 +5 with df",
        "startup": "i17~18",
        "tags": "",
        "target": "m, m",
        "video": ""
    },
    {
        "crush": "",
        "damage": "15",
        "gif": "",
        "id": "Leo-b+1+2",
        "image": "",
        "input": "b+1+2",
        "name": "",
        "notes": "",
        "on_block": "-24~-23",
        "on_ch": "",
        "on_hit": "-11",
        "recovery": "",
        "short_notes": "",
        "startup": "i17~18",
        "tags": "",
        "target": "m",
        "video": ""
    },
    {
        "crush": "",
        "damage": "15, 13",
        "gif": "",
        "id": "Leo-b+1+2,1+2",
        "image": "",
        "input": "b+1+2,1+2",
        "name": "",
        "notes": "Combo from 1st hit",
        "on_block": "-14~-13",
        "on_ch": "+7",
        "on_hit": "-3",
        "recovery": "",
        "short_notes": "Combo from 1st hit",
        "startup": "i21~22",
        "tags": "",
        "target": "m, m",
        "video": ""
    },
    {
        "crush": "",
        "damage": "15, 13, 30",
        "gif": "",
        "id": "Leo-b+1+2,1+2,d,df,f+2",
        "image": "",
        "input": "b+1+2,1+2,d,df,f+2",
        "name": "Jin Gang Hua Shan Tuo Tian Zhang",
        "notes": "* Combo from 2nd CH\n* Chip damage on block\n* Deals 25 damage without motion input",
        "on_block": "-13~-12",
        "on_ch": "",
        "on_hit": "+17d (+12)",
        "recovery": "",
        "short_notes": "* Combo from 2nd CH\n* Deals 25 damage without motion input",
        "startup": "i20~21",
        "tags": "chp",
        "target": "m, m, m",
        "video": ""
    },
    {
        "crush": "",
        "damage": "6,12",
        "gif": "",
        "id": "Leo-b+1+4",
        "image": "",
        "input": "b+1+4",
        "name": "Cuo Zhang",
        "notes": "",
        "on_block": "-12~-10",
        "on_ch": "+14",
        "on_hit": "+3",
        "recovery": "",
        "short_notes": "",
        "startup": "i19~21",
        "tags": "",
        "target": "h,l",
        "video": ""
    },
    {
        "crush": "ps5?~9?",
        "damage": "21",
        "gif": "",
        "id": "Leo-b+2+3",
        "image": "",
        "input": "b+2+3",
        "name": "Ye Kua",
        "notes": "* Parries high and mid punches\n* Hit after parry is the same as on CH\nParry state 5?~9?",
        "on_block": "-8~-7",
        "on_ch": "+28a",
        "on_hit": "+23g",
        "recovery": "",
        "short_notes": "* Parries high and mid punches\n* Hit after parry is the same as on CH",
        "startup": "i30~31",
        "tags": "ps5?~9?",
        "target": "m",
        "video": ""
    },
    {
        "crush": "",
        "damage": "",
        "gif": "",
        "id": "Leo-b+3+4",
        "image": "",
        "input": "b+3+4",
        "name": "Tu Bu Jin Ji Du Li",
        "notes": "",
        "on_block": "",
        "on_ch": "",
        "on_hit": "",
        "recovery": "KNK",
        "short_notes": "",
        "startup": "",
        "tags": "",
        "target": "",
        "video": ""
    },
    {
        "crush": "ps5~12",
        "damage": "",
        "gif": "",
        "id": "Leo-ub+1",
        "image": "",
        "input": "ub+1",
        "name": "Bao Zhou",
        "notes": "* Parries high and mid kicks\nParry state 5~12",
        "on_block": "",
        "on_ch": "",
        "on_hit": "",
        "recovery": "",
        "short_notes": "* Parries high and mid kicks",
        "startup": "",
        "tags": "ps5~12",
        "target": "",
        "video": ""
    },
    {
        "crush": "",
        "damage": "22",
        "gif": "",
        "id": "Leo-ub+1,P.4",
        "image": "",
        "input": "ub+1,P.4",
        "name": "Bao Zhou Ji Tui",
        "notes": "* Combo from parry",
        "on_block": "-16~-15",
        "on_ch": "",
        "on_hit": "+14c",
        "recovery": "",
        "short_notes": "* Combo from parry",
        "startup": "i17~18",
        "tags": "",
        "target": "h",
        "video": ""
    },
    {
        "crush": "js9~",
        "damage": "26",
        "gif": "",
        "id": "Leo-ub+3",
        "image": "",
        "input": "ub+3",
        "name": "Sky Vibration",
        "notes": "Low crush 9~",
        "on_block": "+0c~+3c",
        "on_ch": "+53a",
        "on_hit": "+6c",
        "recovery": "",
        "short_notes": "",
        "startup": "i24~27",
        "tags": "js9~",
        "target": "M",
        "video": ""
    },
    {
        "crush": "js9~",
        "damage": "15",
        "gif": "",
        "id": "Leo-ub+4",
        "image": "",
        "input": "ub+4",
        "name": "Yue Bu San Jing Ti",
        "notes": "* Balcony Break\nLow crush 9~",
        "on_block": "-13~-12",
        "on_ch": "+33a (+23)",
        "on_hit": "+19a (+9)",
        "recovery": "",
        "short_notes": "",
        "startup": "i15~16",
        "tags": "bbr js9~",
        "target": "m",
        "video": ""
    },
    {
        "crush": "",
        "damage": "60",
        "gif": "",
        "id": "Leo-ub+1+2",
        "image": "",
        "input": "ub+1+2",
        "name": "Xiao Jia Er Lu Liang Yi Zhou",
        "notes": "",
        "on_block": "",
        "on_ch": "",
        "on_hit": "+26a (-21)",
        "recovery": "",
        "short_notes": "",
        "startup": "i70~71",
        "tags": "",
        "target": "m!",
        "video": ""
    },
    {
        "crush": "",
        "damage": "17",
        "gif": "",
        "id": "Leo-u+1",
        "image": "",
        "input": "u+1",
        "name": "Xiang Quan",
        "notes": "* Tornado\n* Balcony Break\n** CH only\n** Doesn't Balcony Break on airborne",
        "on_block": "-6~-5",
        "on_ch": "+22a (+5)",
        "on_hit": "+2",
        "recovery": "",
        "short_notes": "** CH only\n** Doesn't Balcony Break on airborne",
        "startup": "i19~20",
        "tags": "trn bbr",
        "target": "m",
        "video": ""
    },
    {
        "crush": "",
        "damage": "8",
        "gif": "",
        "id": "Leo-uf+1",
        "image": "",
        "input": "uf+1",
        "name": "",
        "notes": "",
        "on_block": "-1",
        "on_ch": "",
        "on_hit": "+6",
        "recovery": "",
        "short_notes": "",
        "startup": "i13",
        "tags": "",
        "target": "h",
        "video": ""
    },
    {
        "crush": "",
        "damage": "8, 17",
        "gif": "",
        "id": "Leo-uf+1,1",
        "image": "",
        "input": "uf+1,1",
        "name": "Li Xiang Quan",
        "notes": "* Tornado\n* Balcony Break\n** CH only\n** Doesn't Balcony Break on airborne",
        "on_block": "-6~-5",
        "on_ch": "+22a (+5)",
        "on_hit": "+2",
        "recovery": "",
        "short_notes": "** CH only\n** Doesn't Balcony Break on airborne",
        "startup": "i19~20",
        "tags": "trn bbr",
        "target": "h, m",
        "video": ""
    },
    {
        "crush": "",
        "damage": "8, 25",
        "gif": "",
        "id": "Leo-uf+1,2",
        "image": "",
        "input": "uf+1,2",
        "name": "Chuan Chong Quan",
        "notes": "Balcony Break\n* Combo from 1st hit\n* Gain LTG +22g on hit with 1+2",
        "on_block": "-14~-13",
        "on_ch": "",
        "on_hit": "+37d (-21)",
        "recovery": "",
        "short_notes": "* Combo from 1st hit\n* Gain LTG +22g on hit with 1+2",
        "startup": "i20~21",
        "tags": "bbr",
        "target": "h, m",
        "video": ""
    },
    {
        "crush": "js20~",
        "damage": "15",
        "gif": "",
        "id": "Leo-uf+2",
        "image": "",
        "input": "uf+2",
        "name": "",
        "notes": "* Enter BOK -11 [[Leo combos#Mini-combos|+21a (+14)]] with d\nLow crush 20~",
        "on_block": "-14~-11",
        "on_ch": "",
        "on_hit": "+18a (+11)",
        "recovery": "",
        "short_notes": "* Enter BOK -11 [[Leo combos#Mini-combos|+21a (+14)]] with d",
        "startup": "i18~21",
        "tags": "js20~",
        "target": "m",
        "video": ""
    },
    {
        "crush": "js0~12",
        "damage": "15, 17",
        "gif": "",
        "id": "Leo-uf+2,1",
        "image": "",
        "input": "uf+2,1",
        "name": "Yue Bu Si Quan",
        "notes": "* Combo from 1st hit\n** [[Leo combos#Mini-combos|+23a (+16)]]\nLow crush 0~12",
        "on_block": "-8~-7",
        "on_ch": "+32d",
        "on_hit": "+4",
        "recovery": "",
        "short_notes": "* Combo from 1st hit\n** [[Leo combos#Mini-combos|+23a (+16)]]",
        "startup": "i25~26",
        "tags": "js0~12",
        "target": "m, m",
        "video": ""
    },
    {
        "crush": "js9~",
        "damage": "21",
        "gif": "",
        "id": "Leo-uf+3",
        "image": "",
        "input": "uf+3",
        "name": "Yi Qi Jiao",
        "notes": "Balcony Break\n* Can input with u+3\n** Less forward movement and deals 20 damage\nLow crush 9~",
        "on_block": "-9~-5",
        "on_ch": "",
        "on_hit": "+13a (+4)",
        "recovery": "",
        "short_notes": "* Can input with u+3\n** Less forward movement and deals 20 damage",
        "startup": "i17~21",
        "tags": "bbr js9~",
        "target": "m",
        "video": ""
    },
    {
        "crush": "js9~",
        "damage": "15",
        "gif": "",
        "id": "Leo-uf+4",
        "image": "",
        "input": "uf+4",
        "name": "Yue Bu San Jing Ti",
        "notes": "* Can input with u+4\n** Less forward movement\nLow crush 9~",
        "on_block": "-13~-12",
        "on_ch": "",
        "on_hit": "+33a (+23)",
        "recovery": "",
        "short_notes": "* Can input with u+4\n** Less forward movement",
        "startup": "i15~16",
        "tags": "js9~",
        "target": "m",
        "video": ""
    },
    {
        "crush": "",
        "damage": "",
        "gif": "",
        "id": "Leo-1+2+3+4",
        "image": "",
        "input": "1+2+3+4",
        "name": "Ki Charge",
        "notes": "Gain LTG",
        "on_block": "",
        "on_ch": "",
        "on_hit": "",
        "recovery": "",
        "short_notes": "Gain LTG",
        "startup": "",
        "tags": "",
        "target": "",
        "video": ""
    },
    {
        "crush": "",
        "damage": "",
        "gif": "",
        "id": "Leo-d,df",
        "image": "",
        "input": "d,DF",
        "name": "Jin Bu (Crouching state ver.)",
        "notes": "Crouching state",
        "on_block": "",
        "on_ch": "",
        "on_hit": "",
        "recovery": "",
        "short_notes": "Crouching state",
        "startup": "",
        "tags": "",
        "target": "",
        "video": ""
    },
    {
        "crush": "",
        "damage": "",
        "gif": "",
        "id": "Leo-d,df,f",
        "image": "",
        "input": "d,df,f",
        "name": "Jin Bu",
        "notes": "No crouching state",
        "on_block": "",
        "on_ch": "",
        "on_hit": "",
        "recovery": "",
        "short_notes": "No crouching state",
        "startup": "",
        "tags": "",
        "target": "",
        "video": ""
    },
    {
        "crush": "",
        "damage": "25",
        "gif": "",
        "id": "Leo-f,F+2",
        "image": "",
        "input": "f,F+2",
        "name": "Shang Bu Zhuang Quan",
        "notes": "* Balcony Break\n* Gain LTG -9a on hit with 1+2",
        "on_block": "-9~-8",
        "on_ch": "",
        "on_hit": "+8a",
        "recovery": "",
        "short_notes": "* Gain LTG -9a on hit with 1+2",
        "startup": "i14~15",
        "tags": "bbr",
        "target": "m",
        "video": ""
    },
    {
        "crush": "js9~",
        "damage": "20",
        "gif": "",
        "id": "Leo-f,F+3",
        "image": "",
        "input": "f,F+3",
        "name": "Tiao Shan Fu Ren",
        "notes": "* Enter BOK +0 [[Leo combos#Mini-combos|+10d]] with d\nLow crush 9~",
        "on_block": "-7c~-4c",
        "on_ch": "",
        "on_hit": "+3d",
        "recovery": "",
        "short_notes": "* Enter BOK +0 [[Leo combos#Mini-combos|+10d]] with d",
        "startup": "i26~29",
        "tags": "js9~",
        "target": "m",
        "video": ""
    },
    {
        "crush": "js17",
        "damage": "12",
        "gif": "",
        "id": "Leo-f,F+4",
        "image": "",
        "input": "f,F+4",
        "name": "",
        "notes": "Low crush 17",
        "on_block": "-13",
        "on_ch": "",
        "on_hit": "+28a (+18)",
        "recovery": "",
        "short_notes": "",
        "startup": "i19",
        "tags": "js17",
        "target": "m",
        "video": ""
    },
    {
        "crush": "js0~12",
        "damage": "12, 23",
        "gif": "",
        "id": "Leo-f,F+4,3",
        "image": "",
        "input": "f,F+4,3",
        "name": "",
        "notes": "* Balcony Break\n* Jail from 1st block\n* Combo from 1st hit [[Leo combos#Staples|+28a (+21)]]\nLow crush 0~12",
        "on_block": "-14",
        "on_ch": "",
        "on_hit": "+20 (+11)",
        "recovery": "",
        "short_notes": "* Jail from 1st block\n* Combo from 1st hit [[Leo combos#Staples|+28a (+21)]]",
        "startup": "i12",
        "tags": "bbr js0~12",
        "target": "m, h",
        "video": ""
    },
    {
        "crush": "js0~7, fs8~10, cs20~",
        "damage": "12, 23, 17",
        "gif": "",
        "id": "Leo-f,F+4,3,4",
        "image": "",
        "input": "f,F+4,3,4",
        "name": "",
        "notes": "* Can combo from 1st hit on wall\nLow crush 0~7, fs8~10, High crush 20~",
        "on_block": "-14~-12",
        "on_ch": "+30a",
        "on_hit": "-1",
        "recovery": "",
        "short_notes": "* Can combo from 1st hit on wall",
        "startup": "i29~31",
        "tags": "js0~7 fs8~10 cs20~",
        "target": "m, h, L",
        "video": ""
    },
    {
        "crush": "js9~",
        "damage": "20",
        "gif": "",
        "id": "Leo-uf,n,4",
        "image": "",
        "input": "uf,n,4",
        "name": "Delayed Rising Toe Kick",
        "notes": "Low crush 9~",
        "on_block": "-13~-11",
        "on_ch": "",
        "on_hit": "+32a (+22)",
        "recovery": "",
        "short_notes": "",
        "startup": "i23~25",
        "tags": "js9~",
        "target": "m",
        "video": ""
    },
    {
        "crush": "js3~",
        "damage": "30",
        "gif": "",
        "id": "Leo-f,f,F+3",
        "image": "",
        "input": "f,f,F+3",
        "name": "Tiao Shan Jiang Jiao",
        "notes": "* Balcony Break\n* Alternate input wr3\nLow crush 3~",
        "on_block": "+6~+9",
        "on_ch": "",
        "on_hit": "+13a (+3)",
        "recovery": "",
        "short_notes": "* Alternate input wr3",
        "startup": "i23~26",
        "tags": "bbr js3~",
        "target": "m",
        "video": ""
    },
    {
        "crush": "",
        "damage": "13",
        "gif": "",
        "id": "Leo-ws1",
        "image": "",
        "input": "ws1",
        "name": "",
        "notes": "",
        "on_block": "-8~-7",
        "on_ch": "",
        "on_hit": "+4",
        "recovery": "",
        "short_notes": "",
        "startup": "i14~15",
        "tags": "",
        "target": "m",
        "video": ""
    },
    {
        "crush": "",
        "damage": "13, 12",
        "gif": "",
        "id": "Leo-ws1,4",
        "image": "",
        "input": "ws1,4",
        "name": "",
        "notes": "Combo from 1st CH",
        "on_block": "-12~-11",
        "on_ch": "",
        "on_hit": "-1",
        "recovery": "",
        "short_notes": "Combo from 1st CH",
        "startup": "i19~20",
        "tags": "",
        "target": "m, L",
        "video": ""
    },
    {
        "crush": "",
        "damage": "13, 12, 24",
        "gif": "",
        "id": "Leo-ws1,4,1",
        "image": "",
        "input": "ws1,4,1",
        "name": "Huo Da Ding Zhou",
        "notes": "* Balcony Break\n* Combo from 2nd CH",
        "on_block": "-14",
        "on_ch": "+44a (-3)",
        "on_hit": "+12a (+3)",
        "recovery": "",
        "short_notes": "* Combo from 2nd CH",
        "startup": "i22",
        "tags": "bbr",
        "target": "m, L, m",
        "video": ""
    },
    {
        "crush": "",
        "damage": "17",
        "gif": "",
        "id": "Leo-ws2",
        "image": "",
        "input": "ws2",
        "name": "Shang Bu Gua Shan",
        "notes": "",
        "on_block": "-13~-12",
        "on_ch": "",
        "on_hit": "+28a (+18)",
        "recovery": "",
        "short_notes": "",
        "startup": "i15~16",
        "tags": "",
        "target": "m",
        "video": ""
    },
    {
        "crush": "",
        "damage": "9",
        "gif": "",
        "id": "Leo-ws3",
        "image": "",
        "input": "ws3",
        "name": "",
        "notes": "Alternate input CD.3",
        "on_block": "-6~-5",
        "on_ch": "",
        "on_hit": "+5",
        "recovery": "",
        "short_notes": "Alternate input CD.3",
        "startup": "i13~14",
        "tags": "",
        "target": "M",
        "video": ""
    },
    {
        "crush": "",
        "damage": "9, 9",
        "gif": "",
        "id": "Leo-ws3,1",
        "image": "",
        "input": "ws3,1",
        "name": "",
        "notes": "* Combo from 1st hit\n* Enter BOK -10 +9 with d\n* Alternate input CD.3,1",
        "on_block": "-10",
        "on_ch": "",
        "on_hit": "+3",
        "recovery": "",
        "short_notes": "* Combo from 1st hit\n* Enter BOK -10 +9 with d\n* Alternate input CD.3,1",
        "startup": "i21",
        "tags": "",
        "target": "M, m",
        "video": ""
    },
    {
        "crush": "",
        "damage": "9, 9, 20",
        "gif": "",
        "id": "Leo-ws3,1,2",
        "image": "",
        "input": "ws3,1,2",
        "name": "Liang Yi Er Yui Ya Zhou",
        "notes": "* Combo from 1st CH\n* Alternate input CD.3,1,2",
        "on_block": "-9~-8",
        "on_ch": "+31d (+23)",
        "on_hit": "+6d",
        "recovery": "",
        "short_notes": "* Combo from 1st CH\n* Alternate input CD.3,1,2",
        "startup": "i24~25",
        "tags": "",
        "target": "M, m, h",
        "video": ""
    },
    {
        "crush": "",
        "damage": "8",
        "gif": "",
        "id": "Leo-ws4",
        "image": "",
        "input": "ws4",
        "name": "",
        "notes": "Alternate input CD.4",
        "on_block": "-9~-8",
        "on_ch": "",
        "on_hit": "+2",
        "recovery": "",
        "short_notes": "Alternate input CD.4",
        "startup": "i11~12",
        "tags": "",
        "target": "m",
        "video": ""
    },
    {
        "crush": "",
        "damage": "8, 18",
        "gif": "",
        "id": "Leo-ws4,1+2",
        "image": "",
        "input": "ws4,1+2",
        "name": "Rising Bei Zhe Kao",
        "notes": "* Heat Engager\n\n* Heat Dash +5 [[Leo combos#Mini-combos|+43a (+35)]]\n\n* Combo from 1st hit\n* Alternate input CD.4,1+2",
        "on_block": "-12~-10",
        "on_ch": "",
        "on_hit": "+4d",
        "recovery": "",
        "short_notes": "\n* Heat Dash +5 [[Leo combos#Mini-combos|+43a (+35)]]\n\n* Combo from 1st hit\n* Alternate input CD.4,1+2",
        "startup": "i25~27",
        "tags": "he",
        "target": "m, m",
        "video": ""
    },
    {
        "crush": "",
        "damage": "25",
        "gif": "",
        "id": "Leo-ws1+2",
        "image": "",
        "input": "ws1+2",
        "name": "Le Kua Kao",
        "notes": "* Gain LTG +3 on hit with 1+2\n* Alternate input CD.1+2",
        "on_block": "-15~-13",
        "on_ch": "",
        "on_hit": "+22g",
        "recovery": "",
        "short_notes": "* Gain LTG +3 on hit with 1+2\n* Alternate input CD.1+2",
        "startup": "i13~15",
        "tags": "",
        "target": "m",
        "video": ""
    },
    {
        "crush": "",
        "damage": "30",
        "gif": "",
        "id": "Leo-SS.1+2",
        "image": "",
        "input": "SS.1+2",
        "name": "Da Kai",
        "notes": "* Balcony Break",
        "on_block": "-9",
        "on_ch": "+29d",
        "on_hit": "+14a (+5)",
        "recovery": "",
        "short_notes": "",
        "startup": "i19",
        "tags": "bbr",
        "target": "m",
        "video": ""
    },
    {
        "crush": "",
        "damage": "20",
        "gif": "",
        "id": "Leo-FC.df+3",
        "image": "",
        "input": "FC.df+3",
        "name": "Hou Sao Xuan",
        "notes": "",
        "on_block": "-26~-24",
        "on_ch": "",
        "on_hit": "+37a",
        "recovery": "",
        "short_notes": "",
        "startup": "i21~23",
        "tags": "",
        "target": "L",
        "video": ""
    },
    {
        "crush": "cs0~13",
        "damage": "14",
        "gif": "",
        "id": "Leo-BOK.1",
        "image": "",
        "input": "BOK.1",
        "name": "",
        "notes": "High crush 0~13",
        "on_block": "-4",
        "on_ch": "",
        "on_hit": "+9",
        "recovery": "",
        "short_notes": "",
        "startup": "i13",
        "tags": "cs0~13",
        "target": "m",
        "video": ""
    },
    {
        "crush": "",
        "damage": "14, 20",
        "gif": "",
        "id": "Leo-BOK.1,2",
        "image": "",
        "input": "BOK.1,2",
        "name": "Ya Sui Ying Quan",
        "notes": "* Tornado\n* Combo from 1st hit",
        "on_block": "-14~-13",
        "on_ch": "",
        "on_hit": "+72 (+56)",
        "recovery": "",
        "short_notes": "* Combo from 1st hit",
        "startup": "i17~18",
        "tags": "trn",
        "target": "m, m",
        "video": ""
    },
    {
        "crush": "cs0~19",
        "damage": "23",
        "gif": "",
        "id": "Leo-BOK.2",
        "image": "",
        "input": "BOK.2",
        "name": "Fan Lan Chui",
        "notes": "High crush 0~19",
        "on_block": "-9~-8",
        "on_ch": "",
        "on_hit": "+41a (+31)",
        "recovery": "",
        "short_notes": "",
        "startup": "i19~20",
        "tags": "cs0~19",
        "target": "M",
        "video": ""
    },
    {
        "crush": "js10~",
        "damage": "30",
        "gif": "",
        "id": "Leo-BOK.3",
        "image": "",
        "input": "BOK.3",
        "name": "Startled Crane",
        "notes": "* Homing\n* Balcony Break\n* Chip damage on block\nLow crush 10~",
        "on_block": "+5",
        "on_ch": "",
        "on_hit": "+15d",
        "recovery": "",
        "short_notes": "",
        "startup": "i21",
        "tags": "hom bbr chp js10~",
        "target": "h",
        "video": ""
    },
    {
        "crush": "",
        "damage": "14",
        "gif": "",
        "id": "Leo-BOK.4",
        "image": "",
        "input": "BOK.4",
        "name": "Jin Ji Du Li",
        "notes": "* Same move as [[Leo movelist#Leo-f+4|f+4]]",
        "on_block": "+9",
        "on_ch": "+19",
        "on_hit": "+15g",
        "recovery": "KNK",
        "short_notes": "* Same move as [[Leo movelist#Leo-f+4|f+4]]",
        "startup": "i20",
        "tags": "",
        "target": "m",
        "video": ""
    },
    {
        "crush": "pc8~",
        "damage": "22",
        "gif": "",
        "id": "Leo-BOK.1+2",
        "image": "",
        "input": "BOK.1+2",
        "name": "Lao Pao Ba",
        "notes": "* Heat Engager\n\n* Heat Dash +5 [[Leo combos#Mini-combos|+17d]]\n\n* Balcony Break\n* Spike\n* Chip damage on block\nPower crush 8~",
        "on_block": "-12~-11",
        "on_ch": "",
        "on_hit": "+15d",
        "recovery": "",
        "short_notes": "\n* Heat Dash +5 [[Leo combos#Mini-combos|+17d]]\n",
        "startup": "i20~21",
        "tags": "he bbr spk chp pc8~",
        "target": "M",
        "video": ""
    },
    {
        "crush": "cs",
        "damage": "",
        "gif": "",
        "id": "Leo-BOK.n",
        "image": "",
        "input": "BOK.n",
        "name": "Fo Bu (Elapsed)",
        "notes": "High crush",
        "on_block": "",
        "on_ch": "",
        "on_hit": "",
        "recovery": "",
        "short_notes": "",
        "startup": "",
        "tags": "cs",
        "target": "",
        "video": ""
    },
    {
        "crush": "",
        "damage": "21",
        "gif": "",
        "id": "Leo-BT.1+2",
        "image": "",
        "input": "BT.1+2",
        "name": "Tui Bu Dan Yi",
        "notes": "* Balcony Break",
        "on_block": "-20",
        "on_ch": "+22a (-14)",
        "on_hit": "+1a (-8)",
        "recovery": "",
        "short_notes": "",
        "startup": "i11",
        "tags": "bbr",
        "target": "m",
        "video": ""
    },
    {
        "crush": "cs6~",
        "damage": "17",
        "gif": "",
        "id": "Leo-CD.1",
        "image": "",
        "input": "CD.1",
        "name": "Lei Zhang",
        "notes": "High crush 6~",
        "on_block": "-13~-12",
        "on_ch": "+11",
        "on_hit": "-1",
        "recovery": "",
        "short_notes": "",
        "startup": "i18~19",
        "tags": "cs6~",
        "target": "L",
        "video": ""
    },
    {
        "crush": "",
        "damage": "14",
        "gif": "",
        "id": "Leo-CD.2",
        "image": "",
        "input": "CD.2",
        "name": "",
        "notes": "* Enter KNK -9 +9 with b",
        "on_block": "-9",
        "on_ch": "",
        "on_hit": "+9",
        "recovery": "",
        "short_notes": "* Enter KNK -9 +9 with b",
        "startup": "i17",
        "tags": "",
        "target": "m",
        "video": ""
    },
    {
        "crush": "",
        "damage": "14, 17",
        "gif": "",
        "id": "Leo-CD.2,1",
        "image": "",
        "input": "CD.2,1",
        "name": "Lightning Spear",
        "notes": "* Wall Crush on hit +22g\n\n\n* Combo from 1st hit",
        "on_block": "-6~-5",
        "on_ch": "+30d",
        "on_hit": "+10",
        "recovery": "",
        "short_notes": "\n\n* Combo from 1st hit",
        "startup": "i18~19",
        "tags": "wc",
        "target": "m, m",
        "video": ""
    },
    {
        "crush": "js13~",
        "damage": "14, 26",
        "gif": "",
        "id": "Leo-CD.2,4",
        "image": "",
        "input": "CD.2,4",
        "name": "Lightning Skypiercer",
        "notes": "* Balcony Break\n* Combo from 1st hit\nLow crush 13~",
        "on_block": "-4~-1",
        "on_ch": "",
        "on_hit": "+10d (+0)",
        "recovery": "",
        "short_notes": "* Combo from 1st hit",
        "startup": "i25~28",
        "tags": "bbr js13~",
        "target": "m, h",
        "video": ""
    },
    {
        "crush": "js17~",
        "damage": "6,20",
        "gif": "",
        "id": "Leo-CD.3+4",
        "image": "",
        "input": "CD.3+4",
        "name": "Swallow Step",
        "notes": "* Homing\n* Balcony Break\nLow crush 17~",
        "on_block": "-6~-4",
        "on_ch": "",
        "on_hit": "+13g",
        "recovery": "",
        "short_notes": "",
        "startup": "i18~20 i22~24",
        "tags": "hom bbr js17~",
        "target": "m,m",
        "video": ""
    },
    {
        "crush": "",
        "damage": "12",
        "gif": "",
        "id": "Leo-KNK.1",
        "image": "",
        "input": "KNK.1",
        "name": "",
        "notes": "* Enter BOK -7 +4 with d",
        "on_block": "-9",
        "on_ch": "",
        "on_hit": "+2",
        "recovery": "",
        "short_notes": "* Enter BOK -7 +4 with d",
        "startup": "i18",
        "tags": "",
        "target": "h",
        "video": ""
    },
    {
        "crush": "",
        "damage": "12, 17",
        "gif": "",
        "id": "Leo-KNK.1,2",
        "image": "",
        "input": "KNK.1,2",
        "name": "Bai She Tui Chuang",
        "notes": "* Heat Engager\n\n* Heat Dash +5 [[Leo combos#Staples|+36a (+26)]]\n\n* Combo from 1st hit",
        "on_block": "-9",
        "on_ch": "",
        "on_hit": "+17",
        "recovery": "",
        "short_notes": "\n* Heat Dash +5 [[Leo combos#Staples|+36a (+26)]]\n\n* Combo from 1st hit",
        "startup": "i18",
        "tags": "he",
        "target": "h, m",
        "video": ""
    },
    {
        "crush": "",
        "damage": "20",
        "gif": "",
        "id": "Leo-KNK.2",
        "image": "",
        "input": "KNK.2",
        "name": "Heng Quan",
        "notes": "* Balcony Break",
        "on_block": "-4",
        "on_ch": "+58a",
        "on_hit": "+22a (+13)",
        "recovery": "",
        "short_notes": "",
        "startup": "i13",
        "tags": "bbr",
        "target": "h",
        "video": ""
    },
    {
        "crush": "js13~",
        "damage": "13",
        "gif": "",
        "id": "Leo-KNK.3",
        "image": "",
        "input": "KNK.3",
        "name": "Yi Qi Jiao",
        "notes": "Low crush 13~",
        "on_block": "-13",
        "on_ch": "",
        "on_hit": "+28a (+18)",
        "recovery": "",
        "short_notes": "",
        "startup": "i20",
        "tags": "js13~",
        "target": "m",
        "video": ""
    },
    {
        "crush": "js1~",
        "damage": "13, 18",
        "gif": "",
        "id": "Leo-KNK.3,4",
        "image": "",
        "input": "KNK.3,4",
        "name": "Er Qi Jiao",
        "notes": "Tornado\nLow crush 1~",
        "on_block": "-12",
        "on_ch": "",
        "on_hit": "+80a",
        "recovery": "",
        "short_notes": "",
        "startup": "i15",
        "tags": "trn js1~",
        "target": "m, m",
        "video": ""
    },
    {
        "crush": "",
        "damage": "18",
        "gif": "",
        "id": "Leo-KNK.4",
        "image": "",
        "input": "KNK.4",
        "name": "Cuo Ti Fu Ren",
        "notes": "* Spike\n* Enter CD -10 +6c [[Leo combos#Mini-combos|+19d]] with df",
        "on_block": "-12",
        "on_ch": "+17d",
        "on_hit": "+4c",
        "recovery": "",
        "short_notes": "* Enter CD -10 +6c [[Leo combos#Mini-combos|+19d]] with df",
        "startup": "i20",
        "tags": "spk",
        "target": "L",
        "video": ""
    },
    {
        "crush": "",
        "damage": "20",
        "gif": "",
        "id": "Leo-KNK.1+2",
        "image": "",
        "input": "KNK.1+2",
        "name": "Upper Rising Fist",
        "notes": "* Tornado\n* Balcony Break\n** On non-CH grounded connect\n* Chip Damage on Block",
        "on_block": "-6",
        "on_ch": "+41a (+31)",
        "on_hit": "+21",
        "recovery": "",
        "short_notes": "** On non-CH grounded connect",
        "startup": "i25",
        "tags": "trn bbr chp",
        "target": "M",
        "video": ""
    },
    {
        "crush": "cs8~",
        "damage": "24",
        "gif": "",
        "id": "Leo-KNK.3+4",
        "image": "",
        "input": "KNK.3+4",
        "name": "",
        "notes": "High crush 8~",
        "on_block": "-26",
        "on_ch": "",
        "on_hit": "+19d",
        "recovery": "",
        "short_notes": "",
        "startup": "i24",
        "tags": "cs8~",
        "target": "L",
        "video": ""
    },
    {
        "crush": "",
        "damage": "",
        "gif": "",
        "id": "Leo-KNK.DF",
        "image": "",
        "input": "KNK.DF",
        "name": "Jin Bu",
        "notes": "",
        "on_block": "",
        "on_ch": "",
        "on_hit": "",
        "recovery": "r12 CD",
        "short_notes": "",
        "startup": "",
        "tags": "",
        "target": "",
        "video": ""
    },
    {
        "crush": "",
        "damage": "20",
        "gif": "",
        "id": "Leo-OTG.d+3+4",
        "image": "",
        "input": "OTG.d+3+4",
        "name": "Zhen Jiao",
        "notes": "* Spike\n* -2d (-10) on grounded hit",
        "on_block": "-13~-12",
        "on_ch": "",
        "on_hit": "+3",
        "recovery": "",
        "short_notes": "* -2d (-10) on grounded hit",
        "startup": "i21~22",
        "tags": "spk",
        "target": "L",
        "video": ""
    },
    {
        "crush": "cs1~",
        "damage": "5",
        "gif": "",
        "id": "Leo-hFC.1",
        "image": "",
        "input": "hFC.1",
        "name": "Crouch Jab",
        "notes": "* Transition to Standing with f\nHigh crush 1~",
        "on_block": "-5",
        "on_ch": "",
        "on_hit": "+6",
        "recovery": "r24 FC",
        "short_notes": "* Transition to Standing with f",
        "startup": "i10",
        "tags": "cs1~",
        "target": "sl",
        "video": ""
    },
    {
        "crush": "",
        "damage": "8",
        "gif": "",
        "id": "Leo-hFC.2",
        "image": "",
        "input": "hFC.2",
        "name": "Crouch Straight",
        "notes": "",
        "on_block": "-4",
        "on_ch": "",
        "on_hit": "+7",
        "recovery": "",
        "short_notes": "",
        "startup": "i11",
        "tags": "",
        "target": "sl",
        "video": ""
    },
    {
        "crush": "",
        "damage": "10",
        "gif": "",
        "id": "Leo-hFC.3",
        "image": "",
        "input": "hFC.3",
        "name": "Crouch Spin Kick",
        "notes": "",
        "on_block": "-17",
        "on_ch": "",
        "on_hit": "-6",
        "recovery": "",
        "short_notes": "",
        "startup": "i16",
        "tags": "",
        "target": "l",
        "video": ""
    },
    {
        "crush": "",
        "damage": "6",
        "gif": "",
        "id": "Leo-hFC.4",
        "image": "",
        "input": "hFC.4",
        "name": "Crouch Shin Kick",
        "notes": "",
        "on_block": "-15",
        "on_ch": "",
        "on_hit": "-4",
        "recovery": "",
        "short_notes": "",
        "startup": "i12",
        "tags": "",
        "target": "l",
        "video": ""
    },
    {
        "crush": "",
        "damage": "35",
        "gif": "",
        "id": "Leo-1+3",
        "image": "",
        "input": "1+3",
        "name": "Bao Hu Gui Shan",
        "notes": "Throw break 1 or 2",
        "on_block": "-3",
        "on_ch": "",
        "on_hit": "+0d",
        "recovery": "",
        "short_notes": "Throw break 1 or 2",
        "startup": "i12~14",
        "tags": "",
        "target": "t",
        "video": ""
    },
    {
        "crush": "",
        "damage": "35",
        "gif": "",
        "id": "Leo-2+4",
        "image": "",
        "input": "2+4",
        "name": "Dan Yang Da",
        "notes": "* Throw break 1 or 2\n* Side switch on hit\n* Deals 4 more damage at the wall",
        "on_block": "-6",
        "on_ch": "",
        "on_hit": "+0d",
        "recovery": "",
        "short_notes": "* Throw break 1 or 2\n* Side switch on hit\n* Deals 4 more damage at the wall",
        "startup": "i12~14",
        "tags": "",
        "target": "t",
        "video": ""
    },
    {
        "crush": "",
        "damage": "50",
        "gif": "",
        "id": "Leo-Back throw",
        "image": "",
        "input": "Back throw",
        "name": "Yang Di Tou",
        "notes": "* Deals 10 more damage at the wall",
        "on_block": "",
        "on_ch": "",
        "on_hit": "-3d",
        "recovery": "",
        "short_notes": "* Deals 10 more damage at the wall",
        "startup": "i12~14",
        "tags": "",
        "target": "t",
        "video": ""
    },
    {
        "crush": "",
        "damage": "40",
        "gif": "",
        "id": "Leo-Left throw",
        "image": "",
        "input": "Left throw",
        "name": "Chou Bie Zi",
        "notes": "* Throw break 1\n* Side switch on hit\n* Deals 4 more damage at the wall",
        "on_block": "-3",
        "on_ch": "",
        "on_hit": "+0d",
        "recovery": "",
        "short_notes": "* Throw break 1\n* Side switch on hit\n* Deals 4 more damage at the wall",
        "startup": "i12~14",
        "tags": "",
        "target": "t",
        "video": ""
    },
    {
        "crush": "",
        "damage": "40",
        "gif": "",
        "id": "Leo-Right throw",
        "image": "",
        "input": "Right throw",
        "name": "Da Zhe Jiang",
        "notes": "* Throw break 2\n* Side switch on hit",
        "on_block": "-3",
        "on_ch": "",
        "on_hit": "+1d",
        "recovery": "",
        "short_notes": "* Throw break 2\n* Side switch on hit",
        "startup": "i12~14",
        "tags": "",
        "target": "t",
        "video": ""
    },
    {
        "crush": "",
        "damage": "40",
        "gif": "",
        "id": "Leo-uf+1+2",
        "image": "",
        "input": "uf+1+2",
        "name": "Shuang Pai Shou",
        "notes": "* Balcony Break\n* Throw break 1+2\n* Side switch",
        "on_block": "-6",
        "on_ch": "",
        "on_hit": "+8d",
        "recovery": "",
        "short_notes": "* Throw break 1+2\n* Side switch",
        "startup": "i12~14",
        "tags": "bbr",
        "target": "t",
        "video": ""
    }
]